[{"source":"Twitter for iPhone","created_at":"2021-01-20T20:36:11.000Z","lang":"en","entities":{"hashtags":[{"start":41,"end":47,"tag":"flood"},{"start":60,"end":73,"tag":"EastDidsbury"},{"start":74,"end":87,"tag":"WestDidsbury"},{"start":92,"end":103,"tag":"Northenden"}],"mentions":[{"start":3,"end":15,"username":"EnvAgencyNW","id":"236338186"}],"annotations":{},"urls":{}},"referenced_tweets":[{"type":"retweeted","id":"1351983472181534720"}],"possibly_sensitive":false,"author_id":"1418393833","public_metrics":{"retweet_count":77,"reply_count":0,"like_count":0,"quote_count":0},"id":"1351991939307069445","text":"RT @EnvAgencyNW: We have issued a severe #flood warning for #EastDidsbury #WestDidsbury and #Northenden which means a threat to life and si…","conversation_id":"1351991939307069445","context_annotations":{},"attachments":{"media_keys":{}}},{"source":"Twitter for Android","created_at":"2021-01-20T20:36:10.000Z","lang":"en","entities":{"hashtags":[{"start":49,"end":58,"tag":"Midlands"}],"mentions":[{"start":3,"end":17,"username":"EnvAgencyMids","id":"229502710"}],"annotations":{},"urls":{}},"referenced_tweets":[{"type":"retweeted","id":"1351800412672827392"}],"possibly_sensitive":false,"author_id":"1004010226474012674","public_metrics":{"retweet_count":71,"reply_count":0,"like_count":0,"quote_count":0},"id":"1351991932562632704","text":"RT @EnvAgencyMids: It’s wet, wet, wet across the #Midlands today (Wednesday). Lots of surface water on roads. Please don’t drive through #f…","conversation_id":"1351991932562632704","context_annotations":{},"attachments":{"media_keys":{}}},{"source":"Twitter for iPhone","created_at":"2021-01-20T20:36:07.000Z","lang":"en","entities":{"hashtags":{},"mentions":[{"start":3,"end":16,"username":"EnvAgencyYNE","id":"222468030"}],"annotations":[{"start":55,"end":64,"probability":0.6162,"type":"Place","normalized_text":"River Ouse"},{"start":69,"end":72,"probability":0.937,"type":"Place","normalized_text":"York"}],"urls":{}},"referenced_tweets":[{"type":"retweeted","id":"1351976173618782211"}],"possibly_sensitive":false,"author_id":"333321518","public_metrics":{"retweet_count":18,"reply_count":0,"like_count":0,"quote_count":0},"id":"1351991920814411777","text":"RT @EnvAgencyYNE: We are expecting river levels on the River Ouse in York to peak on Friday morning at around 4.6-4.8m. We continue to moni…","conversation_id":"1351991920814411777","context_annotations":{},"attachments":{"media_keys":{}}},{"source":"Twitter for Android","created_at":"2021-01-20T20:35:35.000Z","lang":"en","entities":{"hashtags":{},"mentions":[{"start":3,"end":18,"username":"ManCityCouncil","id":"26461381"},{"start":23,"end":32,"username":"gmpolice","id":"21857067"},{"start":39,"end":51,"username":"EnvAgencyNW","id":"236338186"}],"annotations":[{"start":104,"end":111,"probability":0.9452,"type":"Place","normalized_text":"Didsbury"},{"start":114,"end":121,"probability":0.3086,"type":"Place","normalized_text":"Chorlton"},{"start":125,"end":134,"probability":0.3963,"type":"Place","normalized_text":"Northenden"}],"urls":{}},"referenced_tweets":[{"type":"retweeted","id":"1351983587608948737"}],"possibly_sensitive":false,"author_id":"75648838","public_metrics":{"retweet_count":176,"reply_count":0,"like_count":0,"quote_count":0},"id":"1351991786365976579","text":"RT @ManCityCouncil: ⚠️ @gmpolice &amp; @EnvAgencyNW have announced a Severe Flood Warning covering parts of Didsbury, Chorlton &amp; Northenden as…","conversation_id":"1351991786365976579","context_annotations":{},"attachments":{"media_keys":{}}},{"source":"Twitter for Android","created_at":"2021-01-20T20:34:08.000Z","lang":"en","entities":{"hashtags":{},"mentions":[{"start":3,"end":18,"username":"ManCityCouncil","id":"26461381"},{"start":23,"end":32,"username":"gmpolice","id":"21857067"},{"start":39,"end":51,"username":"EnvAgencyNW","id":"236338186"}],"annotations":[{"start":104,"end":111,"probability":0.9452,"type":"Place","normalized_text":"Didsbury"},{"start":114,"end":121,"probability":0.3086,"type":"Place","normalized_text":"Chorlton"},{"start":125,"end":134,"probability":0.3963,"type":"Place","normalized_text":"Northenden"}],"urls":{}},"referenced_tweets":[{"type":"retweeted","id":"1351983587608948737"}],"possibly_sensitive":false,"author_id":"97075069","public_metrics":{"retweet_count":176,"reply_count":0,"like_count":0,"quote_count":0},"id":"1351991421620912129","text":"RT @ManCityCouncil: ⚠️ @gmpolice &amp; @EnvAgencyNW have announced a Severe Flood Warning covering parts of Didsbury, Chorlton &amp; Northenden as…","conversation_id":"1351991421620912129","context_annotations":{},"attachments":{"media_keys":{}}},{"source":"Twitter Web App","created_at":"2021-01-20T20:33:51.000Z","lang":"en","entities":{"hashtags":[{"start":41,"end":47,"tag":"flood"},{"start":60,"end":73,"tag":"EastDidsbury"},{"start":74,"end":87,"tag":"WestDidsbury"},{"start":92,"end":103,"tag":"Northenden"}],"mentions":[{"start":3,"end":15,"username":"EnvAgencyNW","id":"236338186"}],"annotations":{},"urls":{}},"referenced_tweets":[{"type":"retweeted","id":"1351983472181534720"}],"possibly_sensitive":false,"author_id":"1529421373","public_metrics":{"retweet_count":77,"reply_count":0,"like_count":0,"quote_count":0},"id":"1351991351295025152","text":"RT @EnvAgencyNW: We have issued a severe #flood warning for #EastDidsbury #WestDidsbury and #Northenden which means a threat to life and si…","conversation_id":"1351991351295025152","context_annotations":{},"attachments":{"media_keys":{}}},{"source":"Twitter for iPhone","created_at":"2021-01-20T20:33:40.000Z","lang":"en","entities":{"hashtags":{},"mentions":[{"start":3,"end":18,"username":"ManCityCouncil","id":"26461381"},{"start":23,"end":32,"username":"gmpolice","id":"21857067"},{"start":39,"end":51,"username":"EnvAgencyNW","id":"236338186"}],"annotations":[{"start":104,"end":111,"probability":0.9452,"type":"Place","normalized_text":"Didsbury"},{"start":114,"end":121,"probability":0.3086,"type":"Place","normalized_text":"Chorlton"},{"start":125,"end":134,"probability":0.3963,"type":"Place","normalized_text":"Northenden"}],"urls":{}},"referenced_tweets":[{"type":"retweeted","id":"1351983587608948737"}],"possibly_sensitive":false,"author_id":"792099690103840769","public_metrics":{"retweet_count":176,"reply_count":0,"like_count":0,"quote_count":0},"id":"1351991303144407040","text":"RT @ManCityCouncil: ⚠️ @gmpolice &amp; @EnvAgencyNW have announced a Severe Flood Warning covering parts of Didsbury, Chorlton &amp; Northenden as…","conversation_id":"1351991303144407040","context_annotations":{},"attachments":{"media_keys":{}}},{"source":"Twitter Web App","created_at":"2021-01-20T20:33:05.000Z","lang":"en","entities":{"hashtags":{},"mentions":[{"start":0,"end":13,"username":"andyscargill","id":"118803112"},{"start":14,"end":21,"username":"AldiUK","id":"28596803"},{"start":22,"end":35,"username":"CountessPark","id":"4853374523"},{"start":36,"end":52,"username":"GPorterStandard","id":"245280012"},{"start":53,"end":65,"username":"EnvAgencyNW","id":"236338186"},{"start":66,"end":81,"username":"GavinMatthews2","id":"347144884"},{"start":82,"end":95,"username":"thelandtrust","id":"64413314"}],"annotations":{},"urls":{}},"referenced_tweets":[{"type":"replied_to","id":"1351944642057658376"}],"possibly_sensitive":false,"author_id":"104132451","public_metrics":{"retweet_count":0,"reply_count":0,"like_count":0,"quote_count":0},"id":"1351991157417504769","text":"@andyscargill @AldiUK @CountessPark @GPorterStandard @EnvAgencyNW @GavinMatthews2 @thelandtrust Are we expecting raw sewage cascading down our streets or is the infrastructure robust enough to cope?","conversation_id":"1351944642057658376","in_reply_to_user_id":"118803112","context_annotations":[{"domain":{"id":"45","name":"Brand Vertical","description":"Top level entities that describe a Brands industry"},"entity":{"id":"781974596706635776","name":"Retail"}},{"domain":{"id":"46","name":"Brand Category","description":"Categories within Brand Verticals that narrow down the scope of Brands"},"entity":{"id":"781974596157251584","name":"Grocery/Convenience"}},{"domain":{"id":"47","name":"Brand","description":"Brands and Companies"},"entity":{"id":"10040459065","name":"Aldi"}}],"attachments":{"media_keys":{}}},{"source":"Twitter Web App","created_at":"2021-01-20T20:33:02.000Z","lang":"en","entities":{"hashtags":[{"start":41,"end":47,"tag":"flood"},{"start":60,"end":73,"tag":"EastDidsbury"},{"start":74,"end":87,"tag":"WestDidsbury"},{"start":92,"end":103,"tag":"Northenden"}],"mentions":[{"start":3,"end":15,"username":"EnvAgencyNW","id":"236338186"}],"annotations":{},"urls":{}},"referenced_tweets":[{"type":"retweeted","id":"1351983472181534720"}],"possibly_sensitive":false,"author_id":"22203003","public_metrics":{"retweet_count":77,"reply_count":0,"like_count":0,"quote_count":0},"id":"1351991146810060801","text":"RT @EnvAgencyNW: We have issued a severe #flood warning for #EastDidsbury #WestDidsbury and #Northenden which means a threat to life and si…","conversation_id":"1351991146810060801","context_annotations":{},"attachments":{"media_keys":{}}},{"source":"Twitter for iPad","created_at":"2021-01-20T20:32:56.000Z","lang":"en","entities":{"hashtags":[{"start":41,"end":47,"tag":"flood"},{"start":60,"end":73,"tag":"EastDidsbury"},{"start":74,"end":87,"tag":"WestDidsbury"},{"start":92,"end":103,"tag":"Northenden"}],"mentions":[{"start":3,"end":15,"username":"EnvAgencyNW","id":"236338186"}],"annotations":{},"urls":{}},"referenced_tweets":[{"type":"retweeted","id":"1351983472181534720"}],"possibly_sensitive":false,"author_id":"2445468143","public_metrics":{"retweet_count":77,"reply_count":0,"like_count":0,"quote_count":0},"id":"1351991119123513349","text":"RT @EnvAgencyNW: We have issued a severe #flood warning for #EastDidsbury #WestDidsbury and #Northenden which means a threat to life and si…","conversation_id":"1351991119123513349","context_annotations":{},"attachments":{"media_keys":{}}},{"source":"Twitter for iPhone","created_at":"2021-01-20T20:32:37.000Z","lang":"en","entities":{"hashtags":{},"mentions":[{"start":3,"end":18,"username":"ManCityCouncil","id":"26461381"},{"start":23,"end":32,"username":"gmpolice","id":"21857067"},{"start":39,"end":51,"username":"EnvAgencyNW","id":"236338186"}],"annotations":[{"start":104,"end":111,"probability":0.9452,"type":"Place","normalized_text":"Didsbury"},{"start":114,"end":121,"probability":0.3086,"type":"Place","normalized_text":"Chorlton"},{"start":125,"end":134,"probability":0.3963,"type":"Place","normalized_text":"Northenden"}],"urls":{}},"referenced_tweets":[{"type":"retweeted","id":"1351983587608948737"}],"possibly_sensitive":false,"author_id":"20400403","public_metrics":{"retweet_count":176,"reply_count":0,"like_count":0,"quote_count":0},"id":"1351991039263989767","text":"RT @ManCityCouncil: ⚠️ @gmpolice &amp; @EnvAgencyNW have announced a Severe Flood Warning covering parts of Didsbury, Chorlton &amp; Northenden as…","conversation_id":"1351991039263989767","context_annotations":{},"attachments":{"media_keys":{}}},{"source":"Twitter for iPhone","created_at":"2021-01-20T20:32:35.000Z","lang":"en","entities":{"hashtags":{},"mentions":[{"start":3,"end":18,"username":"ManCityCouncil","id":"26461381"},{"start":23,"end":32,"username":"gmpolice","id":"21857067"},{"start":39,"end":51,"username":"EnvAgencyNW","id":"236338186"}],"annotations":[{"start":104,"end":111,"probability":0.9452,"type":"Place","normalized_text":"Didsbury"},{"start":114,"end":121,"probability":0.3086,"type":"Place","normalized_text":"Chorlton"},{"start":125,"end":134,"probability":0.3963,"type":"Place","normalized_text":"Northenden"}],"urls":{}},"referenced_tweets":[{"type":"retweeted","id":"1351983587608948737"}],"possibly_sensitive":false,"author_id":"120267998","public_metrics":{"retweet_count":176,"reply_count":0,"like_count":0,"quote_count":0},"id":"1351991030246215681","text":"RT @ManCityCouncil: ⚠️ @gmpolice &amp; @EnvAgencyNW have announced a Severe Flood Warning covering parts of Didsbury, Chorlton &amp; Northenden as…","conversation_id":"1351991030246215681","context_annotations":{},"attachments":{"media_keys":{}}},{"source":"Twitter for iPhone","created_at":"2021-01-20T20:32:31.000Z","lang":"en","entities":{"hashtags":[{"start":41,"end":47,"tag":"flood"},{"start":60,"end":73,"tag":"EastDidsbury"},{"start":74,"end":87,"tag":"WestDidsbury"},{"start":92,"end":103,"tag":"Northenden"}],"mentions":[{"start":3,"end":15,"username":"EnvAgencyNW","id":"236338186"}],"annotations":{},"urls":{}},"referenced_tweets":[{"type":"retweeted","id":"1351983472181534720"}],"possibly_sensitive":false,"author_id":"20400403","public_metrics":{"retweet_count":77,"reply_count":0,"like_count":0,"quote_count":0},"id":"1351991016472129539","text":"RT @EnvAgencyNW: We have issued a severe #flood warning for #EastDidsbury #WestDidsbury and #Northenden which means a threat to life and si…","conversation_id":"1351991016472129539","context_annotations":{},"attachments":{"media_keys":{}}},{"source":"Twitter for Android","created_at":"2021-01-20T20:32:26.000Z","lang":"en","entities":{"hashtags":{},"mentions":[{"start":3,"end":13,"username":"helenpidd","id":"19000029"},{"start":89,"end":101,"username":"EnvAgencyNW","id":"236338186"}],"annotations":[{"start":48,"end":60,"probability":0.8874,"type":"Place","normalized_text":"West Didsbury"},{"start":66,"end":75,"probability":0.5932,"type":"Place","normalized_text":"Northenden"}],"urls":{}},"referenced_tweets":[{"type":"retweeted","id":"1351985810283909121"}],"possibly_sensitive":false,"author_id":"1556650069","public_metrics":{"retweet_count":29,"reply_count":0,"like_count":0,"quote_count":0},"id":"1351990992451350531","text":"RT @helenpidd: Severe flood warnings issued for West Didsbury and Northenden meaning the @EnvAgencyNW thinks there’s a danger to life. http…","conversation_id":"1351990992451350531","context_annotations":{},"attachments":{"media_keys":{}}},{"source":"Twitter Web App","created_at":"2021-01-20T20:32:24.000Z","lang":"en","entities":{"hashtags":{},"mentions":[{"start":0,"end":10,"username":"helenpidd","id":"19000029"},{"start":11,"end":23,"username":"EnvAgencyNW","id":"236338186"}],"annotations":[{"start":30,"end":39,"probability":0.5859,"type":"Place","normalized_text":"Northenden"}],"urls":{}},"referenced_tweets":[{"type":"replied_to","id":"1351985810283909121"}],"possibly_sensitive":false,"author_id":"1278018320550301698","public_metrics":{"retweet_count":1,"reply_count":2,"like_count":1,"quote_count":0},"id":"1351990986478649345","text":"@helenpidd @EnvAgencyNW We in Northenden in the red zone, we less then a min walk away from the river just waiting game now to see if we are evacuated, police been outside our house for good 4 hours","conversation_id":"1351985810283909121","in_reply_to_user_id":"19000029","context_annotations":{},"attachments":{"media_keys":{}}},{"source":"Twitter for iPhone","created_at":"2021-01-20T20:32:16.000Z","lang":"en","entities":{"hashtags":{},"mentions":[{"start":3,"end":16,"username":"OfficialWXUK","id":"1215834974919766016"},{"start":68,"end":78,"username":"EnvAgency","id":"47331384"}],"annotations":[{"start":98,"end":110,"probability":0.8692,"type":"Place","normalized_text":"East Didsbury"}],"urls":{}},"referenced_tweets":[{"type":"retweeted","id":"1351985740704579585"}],"possibly_sensitive":false,"author_id":"40955130","public_metrics":{"retweet_count":4,"reply_count":0,"like_count":0,"quote_count":0},"id":"1351990951795896322","text":"RT @OfficialWXUK: Two SEVERE FLOOD WARNINGS have been issued by the @EnvAgency\n\n— River Mersey at East Didsbury\n— River Mersey at West Dids…","conversation_id":"1351990951795896322","context_annotations":{},"attachments":{"media_keys":{}}},{"source":"Twitter for iPhone","created_at":"2021-01-20T20:31:45.000Z","lang":"en","entities":{"hashtags":{},"mentions":[{"start":3,"end":18,"username":"ManCityCouncil","id":"26461381"},{"start":23,"end":32,"username":"gmpolice","id":"21857067"},{"start":39,"end":51,"username":"EnvAgencyNW","id":"236338186"}],"annotations":[{"start":104,"end":111,"probability":0.9452,"type":"Place","normalized_text":"Didsbury"},{"start":114,"end":121,"probability":0.3086,"type":"Place","normalized_text":"Chorlton"},{"start":125,"end":134,"probability":0.3963,"type":"Place","normalized_text":"Northenden"}],"urls":{}},"referenced_tweets":[{"type":"retweeted","id":"1351983587608948737"}],"possibly_sensitive":false,"author_id":"35230486","public_metrics":{"retweet_count":176,"reply_count":0,"like_count":0,"quote_count":0},"id":"1351990821260840961","text":"RT @ManCityCouncil: ⚠️ @gmpolice &amp; @EnvAgencyNW have announced a Severe Flood Warning covering parts of Didsbury, Chorlton &amp; Northenden as…","conversation_id":"1351990821260840961","context_annotations":{},"attachments":{"media_keys":{}}},{"source":"Twitter for Android","created_at":"2021-01-20T20:31:19.000Z","lang":"en","entities":{"hashtags":{},"mentions":[{"start":0,"end":13,"username":"EnvAgencyYNE","id":"222468030"},{"start":14,"end":26,"username":"MyDoncaster","id":"329630251"}],"annotations":[{"start":73,"end":75,"probability":0.6589,"type":"Other","normalized_text":"god"}],"urls":{}},"referenced_tweets":[{"type":"replied_to","id":"1351982164313825285"}],"possibly_sensitive":false,"author_id":"483346922","public_metrics":{"retweet_count":0,"reply_count":0,"like_count":0,"quote_count":0},"id":"1351990712905117697","text":"@EnvAgencyYNE @MyDoncaster Think I've now seen it all! This is crazy for god's sake just shut it for a few days.","conversation_id":"1351982164313825285","in_reply_to_user_id":"222468030","context_annotations":{},"attachments":{"media_keys":{}}},{"source":"Twitter for iPhone","created_at":"2021-01-20T20:30:57.000Z","lang":"en","entities":{"hashtags":{},"mentions":[{"start":3,"end":16,"username":"EnvAgencyYNE","id":"222468030"}],"annotations":[{"start":55,"end":64,"probability":0.6162,"type":"Place","normalized_text":"River Ouse"},{"start":69,"end":72,"probability":0.937,"type":"Place","normalized_text":"York"}],"urls":{}},"referenced_tweets":[{"type":"retweeted","id":"1351976173618782211"}],"possibly_sensitive":false,"author_id":"796734451900444672","public_metrics":{"retweet_count":18,"reply_count":0,"like_count":0,"quote_count":0},"id":"1351990620433342465","text":"RT @EnvAgencyYNE: We are expecting river levels on the River Ouse in York to peak on Friday morning at around 4.6-4.8m. We continue to moni…","conversation_id":"1351990620433342465","context_annotations":{},"attachments":{"media_keys":{}}},{"source":"Twitter for iPhone","created_at":"2021-01-20T20:30:47.000Z","lang":"en","entities":{"hashtags":{},"mentions":[{"start":3,"end":16,"username":"EnvAgencyYNE","id":"222468030"}],"annotations":[{"start":111,"end":115,"probability":0.4164,"type":"Organization","normalized_text":"Covid"}],"urls":{}},"referenced_tweets":[{"type":"retweeted","id":"1351982164313825285"}],"possibly_sensitive":false,"author_id":"796734451900444672","public_metrics":{"retweet_count":11,"reply_count":0,"like_count":0,"quote_count":0},"id":"1351990579404673026","text":"RT @EnvAgencyYNE: Our field team was in Old Denaby today putting up temporary barriers to ensure access to the Covid vaccination site is ma…","conversation_id":"1351990579404673026","context_annotations":[{"domain":{"id":"123","name":"Ongoing News Story","description":"Ongoing News Stories like 'Brexit'"},"entity":{"id":"1220701888179359745","name":"COVID-19"}}],"attachments":{"media_keys":{}}},{"source":"Twitter for iPhone","created_at":"2021-01-20T20:30:40.000Z","lang":"en","entities":{"hashtags":{},"mentions":[{"start":3,"end":16,"username":"EnvAgencyYNE","id":"222468030"}],"annotations":[{"start":81,"end":92,"probability":0.8179,"type":"Place","normalized_text":"Temple Manor"}],"urls":{}},"referenced_tweets":[{"type":"retweeted","id":"1351986378444328967"}],"possibly_sensitive":false,"author_id":"796734451900444672","public_metrics":{"retweet_count":9,"reply_count":0,"like_count":0,"quote_count":0},"id":"1351990549700632587","text":"RT @EnvAgencyYNE: We have been bolstering the repairs we are currently making to Temple Manor wash lands in the Lower Aire today, as they f…","conversation_id":"1351990549700632587","context_annotations":{},"attachments":{"media_keys":{}}},{"source":"Twitter for Android","created_at":"2021-01-20T20:30:36.000Z","lang":"en","entities":{"hashtags":{},"mentions":[{"start":3,"end":18,"username":"ManCityCouncil","id":"26461381"},{"start":23,"end":32,"username":"gmpolice","id":"21857067"},{"start":39,"end":51,"username":"EnvAgencyNW","id":"236338186"}],"annotations":[{"start":104,"end":111,"probability":0.9452,"type":"Place","normalized_text":"Didsbury"},{"start":114,"end":121,"probability":0.3086,"type":"Place","normalized_text":"Chorlton"},{"start":125,"end":134,"probability":0.3963,"type":"Place","normalized_text":"Northenden"}],"urls":{}},"referenced_tweets":[{"type":"retweeted","id":"1351983587608948737"}],"possibly_sensitive":false,"author_id":"100081485","public_metrics":{"retweet_count":176,"reply_count":0,"like_count":0,"quote_count":0},"id":"1351990533657423875","text":"RT @ManCityCouncil: ⚠️ @gmpolice &amp; @EnvAgencyNW have announced a Severe Flood Warning covering parts of Didsbury, Chorlton &amp; Northenden as…","conversation_id":"1351990533657423875","context_annotations":{},"attachments":{"media_keys":{}}},{"source":"Tweetbot for iΟS","created_at":"2021-01-20T20:30:20.000Z","lang":"en","entities":{"hashtags":{},"mentions":[{"start":3,"end":18,"username":"ManCityCouncil","id":"26461381"},{"start":23,"end":32,"username":"gmpolice","id":"21857067"},{"start":39,"end":51,"username":"EnvAgencyNW","id":"236338186"}],"annotations":[{"start":104,"end":111,"probability":0.9452,"type":"Place","normalized_text":"Didsbury"},{"start":114,"end":121,"probability":0.3086,"type":"Place","normalized_text":"Chorlton"},{"start":125,"end":134,"probability":0.3963,"type":"Place","normalized_text":"Northenden"}],"urls":{}},"referenced_tweets":[{"type":"retweeted","id":"1351983587608948737"}],"possibly_sensitive":false,"author_id":"280367890","public_metrics":{"retweet_count":176,"reply_count":0,"like_count":0,"quote_count":0},"id":"1351990466322042885","text":"RT @ManCityCouncil: ⚠️ @gmpolice &amp; @EnvAgencyNW have announced a Severe Flood Warning covering parts of Didsbury, Chorlton &amp; Northenden as…","conversation_id":"1351990466322042885","context_annotations":{},"attachments":{"media_keys":{}}},{"source":"Twitter for iPad","created_at":"2021-01-20T20:30:06.000Z","lang":"en","entities":{"hashtags":{},"mentions":[{"start":0,"end":10,"username":"helenpidd","id":"19000029"},{"start":11,"end":25,"username":"AndyBurnhamGM","id":"143779403"},{"start":26,"end":38,"username":"EnvAgencyNW","id":"236338186"}],"annotations":{},"urls":{}},"referenced_tweets":[{"type":"replied_to","id":"1351985810283909121"}],"possibly_sensitive":false,"author_id":"1252635715","public_metrics":{"retweet_count":1,"reply_count":0,"like_count":0,"quote_count":0},"id":"1351990407228514312","text":"@helenpidd @AndyBurnhamGM @EnvAgencyNW Mmmmay be an excuse to bring quarantine in for the positive cases","conversation_id":"1351985810283909121","in_reply_to_user_id":"19000029","context_annotations":[{"domain":{"id":"10","name":"Person","description":"Named people in the world like Nelson Mandela"},"entity":{"id":"1070735188836081664","name":"Andy Burnham","description":"British politician"}},{"domain":{"id":"35","name":"Politician","description":"Politicians in the world, like Joe Biden"},"entity":{"id":"1070735188836081664","name":"Andy Burnham","description":"British politician"}},{"domain":{"id":"123","name":"Ongoing News Story","description":"Ongoing News Stories like 'Brexit'"},"entity":{"id":"1220701888179359745","name":"COVID-19"}}],"attachments":{"media_keys":{}}},{"source":"Twitter Web App","created_at":"2021-01-20T20:30:03.000Z","lang":"en","entities":{"hashtags":[{"start":144,"end":148,"tag":"END"}],"mentions":[{"start":74,"end":86,"username":"EnvAgencyNW","id":"236338186"}],"annotations":[{"start":33,"end":45,"probability":0.8958,"type":"Place","normalized_text":"West Didsbury"},{"start":51,"end":60,"probability":0.642,"type":"Place","normalized_text":"Northenden"}],"urls":[{"start":120,"end":143,"url":"https://t.co/wDaiEs5Hvb","expanded_url":"https://flood-warning-information.service.gov.uk/target-area/01","display_url":"…od-warning-information.service.gov.uk/target-area/01","status":404,"unwound_url":"https://flood-warning-information.service.gov.uk/target-area/01"}]},"referenced_tweets":{},"possibly_sensitive":false,"author_id":"898442239","public_metrics":{"retweet_count":0,"reply_count":0,"like_count":0,"quote_count":0},"id":"1351990394893066240","text":"Severe flood warnings issued for West Didsbury and Northenden meaning the @EnvAgencyNW thinks there’s a danger to life. https://t.co/wDaiEs5Hvb #END","conversation_id":"1351990394893066240","context_annotations":{},"attachments":{"media_keys":{}}},{"source":"Twitter for Android","created_at":"2021-01-20T20:29:59.000Z","lang":"en","entities":{"hashtags":{},"mentions":[{"start":3,"end":16,"username":"EnvAgencyYNE","id":"222468030"}],"annotations":[{"start":111,"end":115,"probability":0.4164,"type":"Organization","normalized_text":"Covid"}],"urls":{}},"referenced_tweets":[{"type":"retweeted","id":"1351982164313825285"}],"possibly_sensitive":false,"author_id":"1057342818","public_metrics":{"retweet_count":11,"reply_count":0,"like_count":0,"quote_count":0},"id":"1351990379499941888","text":"RT @EnvAgencyYNE: Our field team was in Old Denaby today putting up temporary barriers to ensure access to the Covid vaccination site is ma…","conversation_id":"1351990379499941888","context_annotations":[{"domain":{"id":"123","name":"Ongoing News Story","description":"Ongoing News Stories like 'Brexit'"},"entity":{"id":"1220701888179359745","name":"COVID-19"}}],"attachments":{"media_keys":{}}},{"source":"Twitter for iPhone","created_at":"2021-01-20T20:29:56.000Z","lang":"en","entities":{"hashtags":[{"start":41,"end":47,"tag":"flood"},{"start":60,"end":73,"tag":"EastDidsbury"},{"start":74,"end":87,"tag":"WestDidsbury"},{"start":92,"end":103,"tag":"Northenden"}],"mentions":[{"start":3,"end":15,"username":"EnvAgencyNW","id":"236338186"}],"annotations":{},"urls":{}},"referenced_tweets":[{"type":"retweeted","id":"1351983472181534720"}],"possibly_sensitive":false,"author_id":"854302200","public_metrics":{"retweet_count":77,"reply_count":0,"like_count":0,"quote_count":0},"id":"1351990364094275594","text":"RT @EnvAgencyNW: We have issued a severe #flood warning for #EastDidsbury #WestDidsbury and #Northenden which means a threat to life and si…","conversation_id":"1351990364094275594","context_annotations":{},"attachments":{"media_keys":{}}},{"source":"Twitter for Android","created_at":"2021-01-20T20:28:43.000Z","lang":"en","entities":{"hashtags":{},"mentions":[{"start":3,"end":13,"username":"helenpidd","id":"19000029"},{"start":89,"end":101,"username":"EnvAgencyNW","id":"236338186"}],"annotations":[{"start":48,"end":60,"probability":0.8874,"type":"Place","normalized_text":"West Didsbury"},{"start":66,"end":75,"probability":0.5932,"type":"Place","normalized_text":"Northenden"}],"urls":{}},"referenced_tweets":[{"type":"retweeted","id":"1351985810283909121"}],"possibly_sensitive":false,"author_id":"55184447","public_metrics":{"retweet_count":29,"reply_count":0,"like_count":0,"quote_count":0},"id":"1351990058950258688","text":"RT @helenpidd: Severe flood warnings issued for West Didsbury and Northenden meaning the @EnvAgencyNW thinks there’s a danger to life. http…","conversation_id":"1351990058950258688","context_annotations":{},"attachments":{"media_keys":{}}},{"source":"Twitter for Android","created_at":"2021-01-20T20:28:35.000Z","lang":"en","entities":{"hashtags":{},"mentions":[{"start":3,"end":18,"username":"ManCityCouncil","id":"26461381"},{"start":23,"end":32,"username":"gmpolice","id":"21857067"},{"start":39,"end":51,"username":"EnvAgencyNW","id":"236338186"}],"annotations":[{"start":104,"end":111,"probability":0.9452,"type":"Place","normalized_text":"Didsbury"},{"start":114,"end":121,"probability":0.3086,"type":"Place","normalized_text":"Chorlton"},{"start":125,"end":134,"probability":0.3963,"type":"Place","normalized_text":"Northenden"}],"urls":{}},"referenced_tweets":[{"type":"retweeted","id":"1351983587608948737"}],"possibly_sensitive":false,"author_id":"62061564","public_metrics":{"retweet_count":176,"reply_count":0,"like_count":0,"quote_count":0},"id":"1351990026721226759","text":"RT @ManCityCouncil: ⚠️ @gmpolice &amp; @EnvAgencyNW have announced a Severe Flood Warning covering parts of Didsbury, Chorlton &amp; Northenden as…","conversation_id":"1351990026721226759","context_annotations":{},"attachments":{"media_keys":{}}},{"source":"Twitter for iPhone","created_at":"2021-01-20T20:28:34.000Z","lang":"en","entities":{"hashtags":{},"mentions":[{"start":0,"end":15,"username":"robintuddenham","id":"27479955"},{"start":16,"end":28,"username":"VickiSmith_","id":"913098381739925511"},{"start":29,"end":42,"username":"EnvAgencyYNE","id":"222468030"},{"start":43,"end":54,"username":"Calderdale","id":"20065945"},{"start":55,"end":70,"username":"slowtheflow_UK","id":"738462567316770816"},{"start":89,"end":101,"username":"bridgeholme","id":"1125576648013811712"}],"annotations":{},"urls":{}},"referenced_tweets":[{"type":"replied_to","id":"1351975735628595200"}],"possibly_sensitive":false,"author_id":"51977388","public_metrics":{"retweet_count":0,"reply_count":0,"like_count":2,"quote_count":0},"id":"1351990019230228482","text":"@robintuddenham @VickiSmith_ @EnvAgencyYNE @Calderdale @slowtheflow_UK River dropping at @bridgeholme too 😁","conversation_id":"1351975735628595200","in_reply_to_user_id":"27479955","context_annotations":{},"attachments":{"media_keys":{}}},{"source":"Twitter for Android","created_at":"2021-01-20T20:28:13.000Z","lang":"en","entities":{"hashtags":[{"start":41,"end":47,"tag":"flood"},{"start":60,"end":73,"tag":"EastDidsbury"},{"start":74,"end":87,"tag":"WestDidsbury"},{"start":92,"end":103,"tag":"Northenden"}],"mentions":[{"start":3,"end":15,"username":"EnvAgencyNW","id":"236338186"}],"annotations":{},"urls":{}},"referenced_tweets":[{"type":"retweeted","id":"1351983472181534720"}],"possibly_sensitive":false,"author_id":"338493408","public_metrics":{"retweet_count":77,"reply_count":0,"like_count":0,"quote_count":0},"id":"1351989933582508036","text":"RT @EnvAgencyNW: We have issued a severe #flood warning for #EastDidsbury #WestDidsbury and #Northenden which means a threat to life and si…","conversation_id":"1351989933582508036","context_annotations":{},"attachments":{"media_keys":{}}},{"source":"Twitter for iPhone","created_at":"2021-01-20T20:27:48.000Z","lang":"en","entities":{"hashtags":{},"mentions":[{"start":3,"end":18,"username":"robintuddenham","id":"27479955"},{"start":56,"end":69,"username":"EnvAgencyYNE","id":"222468030"},{"start":70,"end":81,"username":"Calderdale","id":"20065945"}],"annotations":{},"urls":{}},"referenced_tweets":[{"type":"retweeted","id":"1351975735628595200"}],"possibly_sensitive":false,"author_id":"51977388","public_metrics":{"retweet_count":12,"reply_count":0,"like_count":0,"quote_count":0},"id":"1351989829102399491","text":"RT @robintuddenham: UPDATE: 7.30pm: Wet &amp; windy day @EnvAgencyYNE @Calderdale defences tested, river &amp; canal been high. Amber warning remai…","conversation_id":"1351989829102399491","context_annotations":{},"attachments":{"media_keys":{}}},{"source":"Twitter for iPhone","created_at":"2021-01-20T20:27:39.000Z","lang":"en","entities":{"hashtags":{},"mentions":[{"start":3,"end":16,"username":"EnvAgencyYNE","id":"222468030"}],"annotations":[{"start":111,"end":115,"probability":0.4164,"type":"Organization","normalized_text":"Covid"}],"urls":{}},"referenced_tweets":[{"type":"retweeted","id":"1351982164313825285"}],"possibly_sensitive":false,"author_id":"792099690103840769","public_metrics":{"retweet_count":11,"reply_count":0,"like_count":0,"quote_count":0},"id":"1351989788958724101","text":"RT @EnvAgencyYNE: Our field team was in Old Denaby today putting up temporary barriers to ensure access to the Covid vaccination site is ma…","conversation_id":"1351989788958724101","context_annotations":[{"domain":{"id":"123","name":"Ongoing News Story","description":"Ongoing News Stories like 'Brexit'"},"entity":{"id":"1220701888179359745","name":"COVID-19"}}],"attachments":{"media_keys":{}}},{"source":"Twitter for iPhone","created_at":"2021-01-20T20:27:16.000Z","lang":"en","entities":{"hashtags":[{"start":80,"end":92,"tag":"partnership"}],"mentions":[{"start":3,"end":18,"username":"WYP_BenDoughty","id":"783320285902766081"},{"start":62,"end":73,"username":"Calderdale","id":"20065945"}],"annotations":{},"urls":{}},"referenced_tweets":[{"type":"retweeted","id":"1351815695110197248"}],"possibly_sensitive":false,"author_id":"1332462559455289349","public_metrics":{"retweet_count":9,"reply_count":0,"like_count":0,"quote_count":0},"id":"1351989692389076993","text":"RT @WYP_BenDoughty: Some more very wet weather on the way for @Calderdale \n\nOur #partnership teams are out monitoring and are prepared to r…","conversation_id":"1351989692389076993","context_annotations":{},"attachments":{"media_keys":{}}},{"source":"Twitter for iPad","created_at":"2021-01-20T20:27:08.000Z","lang":"en","entities":{"hashtags":{},"mentions":[{"start":3,"end":18,"username":"ManCityCouncil","id":"26461381"},{"start":23,"end":32,"username":"gmpolice","id":"21857067"},{"start":39,"end":51,"username":"EnvAgencyNW","id":"236338186"}],"annotations":[{"start":104,"end":111,"probability":0.9452,"type":"Place","normalized_text":"Didsbury"},{"start":114,"end":121,"probability":0.3086,"type":"Place","normalized_text":"Chorlton"},{"start":125,"end":134,"probability":0.3963,"type":"Place","normalized_text":"Northenden"}],"urls":{}},"referenced_tweets":[{"type":"retweeted","id":"1351983587608948737"}],"possibly_sensitive":false,"author_id":"21056196","public_metrics":{"retweet_count":176,"reply_count":0,"like_count":0,"quote_count":0},"id":"1351989659568582663","text":"RT @ManCityCouncil: ⚠️ @gmpolice &amp; @EnvAgencyNW have announced a Severe Flood Warning covering parts of Didsbury, Chorlton &amp; Northenden as…","conversation_id":"1351989659568582663","context_annotations":{},"attachments":{"media_keys":{}}},{"source":"Twitter for iPhone","created_at":"2021-01-20T20:26:51.000Z","lang":"en","entities":{"hashtags":{},"mentions":[{"start":0,"end":13,"username":"WWTworldwide","id":"85337244"},{"start":14,"end":29,"username":"BBCSpringwatch","id":"71229689"},{"start":93,"end":105,"username":"EnvAgencySE","id":"338250767"},{"start":106,"end":119,"username":"CRTSouthEast","id":"93601662"}],"annotations":[{"start":37,"end":56,"probability":0.8136,"type":"Place","normalized_text":"Welsh Harp Reservoir"},{"start":61,"end":77,"probability":0.8784,"type":"Place","normalized_text":"North West London"}],"urls":{}},"referenced_tweets":[{"type":"replied_to","id":"1351988626083733504"}],"possibly_sensitive":false,"author_id":"1038862375674421248","public_metrics":{"retweet_count":0,"reply_count":0,"like_count":0,"quote_count":0},"id":"1351989589435678720","text":"@WWTworldwide @BBCSpringwatch On the Welsh Harp Reservoir in North West London they call out @EnvAgencySE @CRTSouthEast “please clean and dredge our reservoir”","conversation_id":"1351988626083733504","in_reply_to_user_id":"85337244","context_annotations":[{"domain":{"id":"3","name":"TV Shows","description":"Television shows from around the world"},"entity":{"id":"10027336039","name":"Springwatch","description":"Following the fortunes of a cast of unforgettable wildlife characters at the climax of spring."}},{"domain":{"id":"3","name":"TV Shows","description":"Television shows from around the world"},"entity":{"id":"10028610104","name":"Winterwatch","description":"`Winterwatch' continues the BBC's rich tradition of nature documentaries that show off the beauty of the planet and various wildlife species. From their base at the Cairngorms National Park in Scotland, which is twice the size of the Lake District, presenters Chris Packham, Michaela Strachan and Gillian Burke discover ways that the area's animals survive the challenges that come with winter. With short days, plummeting temperatures and a lack of food, cameras monitor the animals' movements. Beavers, pine martens, golden eagles and red squirrels are among the species featured in the programme."}},{"domain":{"id":"4","name":"TV Episodes","description":"Television show episodes"},"entity":{"id":"1347279677925117952","name":"Winterwatch","description":"`Winterwatch' continues the BBC's rich tradition of nature documentaries that show off the beauty of the planet and various wildlife species. From their base at the Cairngorms National Park in Scotland, which is twice the size of the Lake District, presenters Chris Packham, Michaela Strachan and Gillian Burke discover ways that the area's animals survive the challenges that come with winter. With short days, plummeting temperatures and a lack of food, cameras monitor the animals' movements. Beavers, pine martens, golden eagles and red squirrels are among the species featured in the programme."}}],"attachments":{"media_keys":{}}},{"source":"Twitter for iPhone","created_at":"2021-01-20T20:26:46.000Z","lang":"en","entities":{"hashtags":{},"mentions":[{"start":3,"end":18,"username":"robintuddenham","id":"27479955"},{"start":56,"end":69,"username":"EnvAgencyYNE","id":"222468030"},{"start":70,"end":81,"username":"Calderdale","id":"20065945"}],"annotations":{},"urls":{}},"referenced_tweets":[{"type":"retweeted","id":"1351975735628595200"}],"possibly_sensitive":false,"author_id":"913098381739925511","public_metrics":{"retweet_count":12,"reply_count":0,"like_count":0,"quote_count":0},"id":"1351989570360012802","text":"RT @robintuddenham: UPDATE: 7.30pm: Wet &amp; windy day @EnvAgencyYNE @Calderdale defences tested, river &amp; canal been high. Amber warning remai…","conversation_id":"1351989570360012802","context_annotations":{},"attachments":{"media_keys":{}}},{"source":"Twitter for iPhone","created_at":"2021-01-20T20:26:13.000Z","lang":"en","entities":{"hashtags":[{"start":41,"end":47,"tag":"flood"},{"start":60,"end":73,"tag":"EastDidsbury"},{"start":74,"end":87,"tag":"WestDidsbury"},{"start":92,"end":103,"tag":"Northenden"}],"mentions":[{"start":3,"end":15,"username":"EnvAgencyNW","id":"236338186"}],"annotations":{},"urls":{}},"referenced_tweets":[{"type":"retweeted","id":"1351983472181534720"}],"possibly_sensitive":false,"author_id":"209980898","public_metrics":{"retweet_count":77,"reply_count":0,"like_count":0,"quote_count":0},"id":"1351989431213969421","text":"RT @EnvAgencyNW: We have issued a severe #flood warning for #EastDidsbury #WestDidsbury and #Northenden which means a threat to life and si…","conversation_id":"1351989431213969421","context_annotations":{},"attachments":{"media_keys":{}}},{"source":"Twitter for iPad","created_at":"2021-01-20T20:25:52.000Z","lang":"en","entities":{"hashtags":{},"mentions":[{"start":0,"end":12,"username":"jreynoldsMP","id":"18632946"},{"start":13,"end":27,"username":"tmbc_highways","id":"310343497"},{"start":28,"end":40,"username":"EnvAgencyNW","id":"236338186"}],"annotations":[{"start":234,"end":239,"probability":0.6361,"type":"Place","normalized_text":"Mersey"}],"urls":[{"start":321,"end":344,"url":"https://t.co/Yine5EWUvW","expanded_url":"https://twitter.com/GregBroadhurst/status/1351989343850737665/photo/1","display_url":"pic.twitter.com/Yine5EWUvW"},{"start":321,"end":344,"url":"https://t.co/Yine5EWUvW","expanded_url":"https://twitter.com/GregBroadhurst/status/1351989343850737665/photo/1","display_url":"pic.twitter.com/Yine5EWUvW"},{"start":321,"end":344,"url":"https://t.co/Yine5EWUvW","expanded_url":"https://twitter.com/GregBroadhurst/status/1351989343850737665/photo/1","display_url":"pic.twitter.com/Yine5EWUvW"}]},"referenced_tweets":[{"type":"replied_to","id":"1351979761950728193"}],"possibly_sensitive":false,"author_id":"147341694","public_metrics":{"retweet_count":0,"reply_count":0,"like_count":1,"quote_count":0},"id":"1351989343850737665","text":"@jreynoldsMP @tmbc_highways @EnvAgencyNW Bit further downstream earlier in Sale near my offices, rare I see it climb over the first bank, just hoping the signs of gauges upstream levelling out might help avoid worse stuff down in the Mersey basin.\n\nThankfully the second level banks were doing their work this afternoon. https://t.co/Yine5EWUvW","conversation_id":"1351979761950728193","in_reply_to_user_id":"18632946","context_annotations":[{"domain":{"id":"10","name":"Person","description":"Named people in the world like Nelson Mandela"},"entity":{"id":"1070735187045011461","name":"Jonathan Reynolds","description":"British politician"}},{"domain":{"id":"35","name":"Politician","description":"Politicians in the world, like Joe Biden"},"entity":{"id":"1070735187045011461","name":"Jonathan Reynolds","description":"British politician"}}],"attachments":{"media_keys":["3_1351989318458494980","3_1351989318445891585","3_1351989319578361856"]}},{"source":"Twitter for iPad","created_at":"2021-01-20T20:25:50.000Z","lang":"en","entities":{"hashtags":{},"mentions":[{"start":3,"end":13,"username":"helenpidd","id":"19000029"},{"start":89,"end":101,"username":"EnvAgencyNW","id":"236338186"}],"annotations":[{"start":48,"end":60,"probability":0.8874,"type":"Place","normalized_text":"West Didsbury"},{"start":66,"end":75,"probability":0.5932,"type":"Place","normalized_text":"Northenden"}],"urls":{}},"referenced_tweets":[{"type":"retweeted","id":"1351985810283909121"}],"possibly_sensitive":false,"author_id":"326292530","public_metrics":{"retweet_count":29,"reply_count":0,"like_count":0,"quote_count":0},"id":"1351989334438797315","text":"RT @helenpidd: Severe flood warnings issued for West Didsbury and Northenden meaning the @EnvAgencyNW thinks there’s a danger to life. http…","conversation_id":"1351989334438797315","context_annotations":{},"attachments":{"media_keys":{}}},{"source":"Twitter for Android","created_at":"2021-01-20T20:25:47.000Z","lang":"en","entities":{"hashtags":{},"mentions":[{"start":3,"end":18,"username":"ManCityCouncil","id":"26461381"},{"start":23,"end":32,"username":"gmpolice","id":"21857067"},{"start":39,"end":51,"username":"EnvAgencyNW","id":"236338186"}],"annotations":[{"start":104,"end":111,"probability":0.9452,"type":"Place","normalized_text":"Didsbury"},{"start":114,"end":121,"probability":0.3086,"type":"Place","normalized_text":"Chorlton"},{"start":125,"end":134,"probability":0.3963,"type":"Place","normalized_text":"Northenden"}],"urls":{}},"referenced_tweets":[{"type":"retweeted","id":"1351983587608948737"}],"possibly_sensitive":false,"author_id":"476910840","public_metrics":{"retweet_count":176,"reply_count":0,"like_count":0,"quote_count":0},"id":"1351989319746154497","text":"RT @ManCityCouncil: ⚠️ @gmpolice &amp; @EnvAgencyNW have announced a Severe Flood Warning covering parts of Didsbury, Chorlton &amp; Northenden as…","conversation_id":"1351989319746154497","context_annotations":{},"attachments":{"media_keys":{}}},{"source":"Twitter for iPhone","created_at":"2021-01-20T20:25:45.000Z","lang":"en","entities":{"hashtags":[{"start":41,"end":47,"tag":"flood"},{"start":60,"end":73,"tag":"EastDidsbury"},{"start":74,"end":87,"tag":"WestDidsbury"},{"start":92,"end":103,"tag":"Northenden"}],"mentions":[{"start":3,"end":15,"username":"EnvAgencyNW","id":"236338186"}],"annotations":{},"urls":{}},"referenced_tweets":[{"type":"retweeted","id":"1351983472181534720"}],"possibly_sensitive":false,"author_id":"1256200230913048576","public_metrics":{"retweet_count":77,"reply_count":0,"like_count":0,"quote_count":0},"id":"1351989313790160898","text":"RT @EnvAgencyNW: We have issued a severe #flood warning for #EastDidsbury #WestDidsbury and #Northenden which means a threat to life and si…","conversation_id":"1351989313790160898","context_annotations":{},"attachments":{"media_keys":{}}},{"source":"Twitter for iPad","created_at":"2021-01-20T20:25:04.000Z","lang":"en","entities":{"hashtags":{},"mentions":[{"start":3,"end":13,"username":"helenpidd","id":"19000029"},{"start":89,"end":101,"username":"EnvAgencyNW","id":"236338186"}],"annotations":[{"start":48,"end":60,"probability":0.8874,"type":"Place","normalized_text":"West Didsbury"},{"start":66,"end":75,"probability":0.5932,"type":"Place","normalized_text":"Northenden"}],"urls":{}},"referenced_tweets":[{"type":"retweeted","id":"1351985810283909121"}],"possibly_sensitive":false,"author_id":"1326862794","public_metrics":{"retweet_count":29,"reply_count":0,"like_count":0,"quote_count":0},"id":"1351989141223911427","text":"RT @helenpidd: Severe flood warnings issued for West Didsbury and Northenden meaning the @EnvAgencyNW thinks there’s a danger to life. http…","conversation_id":"1351989141223911427","context_annotations":{},"attachments":{"media_keys":{}}},{"source":"Twitter Web App","created_at":"2021-01-20T20:24:59.000Z","lang":"en","entities":{"hashtags":{},"mentions":[{"start":0,"end":16,"username":"HayleyH51368106","id":"1278018320550301698"},{"start":17,"end":32,"username":"ManCityCouncil","id":"26461381"},{"start":33,"end":42,"username":"gmpolice","id":"21857067"},{"start":43,"end":53,"username":"EnvAgency","id":"47331384"}],"annotations":{},"urls":[{"start":80,"end":103,"url":"https://t.co/Q1D17PbAYH","expanded_url":"https://flood-warning-information.service.gov.uk/target-area/013FWFGM35","display_url":"…od-warning-information.service.gov.uk/target-area/01…","images":[{"url":"https://pbs.twimg.com/news_img/1361710183219556352/Zn91S6R0?format=png&name=orig","width":1200,"height":630},{"url":"https://pbs.twimg.com/news_img/1361710183219556352/Zn91S6R0?format=png&name=150x150","width":150,"height":150}],"status":200,"title":"Flood information for River Mersey at West Didsbury and Northenden - GOV.UK","description":"Check your risk of flooding: get current flood warnings, river and sea levels, check the 5-day forecast or use flood risk maps","unwound_url":"https://flood-warning-information.service.gov.uk/target-area/013FWFGM35"}]},"referenced_tweets":[{"type":"replied_to","id":"1351988856862765058"}],"possibly_sensitive":false,"author_id":"236338186","public_metrics":{"retweet_count":9,"reply_count":0,"like_count":6,"quote_count":0},"id":"1351989119895920640","text":"@HayleyH51368106 @ManCityCouncil @gmpolice @EnvAgency You can see the area here https://t.co/Q1D17PbAYH","conversation_id":"1351983587608948737","in_reply_to_user_id":"1278018320550301698","context_annotations":{},"attachments":{"media_keys":{}}},{"source":"Twitter for iPhone","created_at":"2021-01-20T20:24:51.000Z","lang":"en","entities":{"hashtags":{},"mentions":[{"start":3,"end":16,"username":"EnvAgencyYNE","id":"222468030"}],"annotations":[{"start":34,"end":43,"probability":0.7407,"type":"Place","normalized_text":"Calderdale"}],"urls":{}},"referenced_tweets":[{"type":"retweeted","id":"1351975002632048643"}],"possibly_sensitive":false,"author_id":"1461581809","public_metrics":{"retweet_count":14,"reply_count":0,"like_count":0,"quote_count":0},"id":"1351989087318773760","text":"RT @EnvAgencyYNE: River levels in Calderdale are still responding to current rainfall and will remain high in the upper parts of the catchm…","conversation_id":"1351989087318773760","context_annotations":{},"attachments":{"media_keys":{}}},{"source":"Echofon","created_at":"2021-01-20T20:24:47.000Z","lang":"en","entities":{"hashtags":{},"mentions":[{"start":3,"end":18,"username":"ManCityCouncil","id":"26461381"},{"start":23,"end":32,"username":"gmpolice","id":"21857067"},{"start":39,"end":51,"username":"EnvAgencyNW","id":"236338186"}],"annotations":[{"start":104,"end":111,"probability":0.9452,"type":"Place","normalized_text":"Didsbury"},{"start":114,"end":121,"probability":0.3086,"type":"Place","normalized_text":"Chorlton"},{"start":125,"end":134,"probability":0.3963,"type":"Place","normalized_text":"Northenden"}],"urls":{}},"referenced_tweets":[{"type":"retweeted","id":"1351983587608948737"}],"possibly_sensitive":false,"author_id":"18951643","public_metrics":{"retweet_count":176,"reply_count":0,"like_count":0,"quote_count":0},"id":"1351989069182607367","text":"RT @ManCityCouncil: ⚠️ @gmpolice &amp; @EnvAgencyNW have announced a Severe Flood Warning covering parts of Didsbury, Chorlton &amp; Northenden as…","conversation_id":"1351989069182607367","context_annotations":[{"domain":{"id":"10","name":"Person","description":"Named people in the world like Nelson Mandela"},"entity":{"id":"1070735207228092417","name":"Jeff Smith","description":"British politician"}},{"domain":{"id":"35","name":"Politician","description":"Politicians in the world, like Joe Biden"},"entity":{"id":"1070735207228092417","name":"Jeff Smith","description":"British politician"}}],"attachments":{"media_keys":{}}},{"source":"Twitter for Android","created_at":"2021-01-20T20:24:29.000Z","lang":"en","entities":{"hashtags":{},"mentions":[{"start":3,"end":18,"username":"robintuddenham","id":"27479955"},{"start":56,"end":69,"username":"EnvAgencyYNE","id":"222468030"},{"start":70,"end":81,"username":"Calderdale","id":"20065945"}],"annotations":{},"urls":{}},"referenced_tweets":[{"type":"retweeted","id":"1351975735628595200"}],"possibly_sensitive":false,"author_id":"3451023201","public_metrics":{"retweet_count":12,"reply_count":0,"like_count":0,"quote_count":0},"id":"1351988994280747029","text":"RT @robintuddenham: UPDATE: 7.30pm: Wet &amp; windy day @EnvAgencyYNE @Calderdale defences tested, river &amp; canal been high. Amber warning remai…","conversation_id":"1351988994280747029","context_annotations":{},"attachments":{"media_keys":{}}},{"source":"Twitter for Android","created_at":"2021-01-20T20:24:24.000Z","lang":"en","entities":{"hashtags":{},"mentions":[{"start":3,"end":18,"username":"ManCityCouncil","id":"26461381"},{"start":23,"end":32,"username":"gmpolice","id":"21857067"},{"start":39,"end":51,"username":"EnvAgencyNW","id":"236338186"}],"annotations":[{"start":104,"end":111,"probability":0.9452,"type":"Place","normalized_text":"Didsbury"},{"start":114,"end":121,"probability":0.3086,"type":"Place","normalized_text":"Chorlton"},{"start":125,"end":134,"probability":0.3963,"type":"Place","normalized_text":"Northenden"}],"urls":{}},"referenced_tweets":[{"type":"retweeted","id":"1351983587608948737"}],"possibly_sensitive":false,"author_id":"1305069979038035968","public_metrics":{"retweet_count":176,"reply_count":0,"like_count":0,"quote_count":0},"id":"1351988974521380864","text":"RT @ManCityCouncil: ⚠️ @gmpolice &amp; @EnvAgencyNW have announced a Severe Flood Warning covering parts of Didsbury, Chorlton &amp; Northenden as…","conversation_id":"1351988974521380864","context_annotations":{},"attachments":{"media_keys":{}}},{"source":"Twitter for iPhone","created_at":"2021-01-20T20:24:04.000Z","lang":"en","entities":{"hashtags":{},"mentions":[{"start":3,"end":18,"username":"React_Response","id":"3185165022"},{"start":129,"end":139,"username":"EnvAgency","id":"47331384"}],"annotations":[{"start":69,"end":83,"probability":0.8262,"type":"Person","normalized_text":"Storm Christoph"}],"urls":{}},"referenced_tweets":[{"type":"retweeted","id":"1351892781816492032"}],"possibly_sensitive":false,"author_id":"131596278","public_metrics":{"retweet_count":12,"reply_count":0,"like_count":0,"quote_count":0},"id":"1351988887627976710","text":"RT @React_Response: With flood warnings across the country caused by Storm Christoph, make sure you're prepared by following the @EnvAgency…","conversation_id":"1351988887627976710","context_annotations":{},"attachments":{"media_keys":{}}},{"source":"Twitter Web App","created_at":"2021-01-20T20:23:56.000Z","lang":"en","entities":{"hashtags":{},"mentions":[{"start":0,"end":15,"username":"ManCityCouncil","id":"26461381"},{"start":16,"end":25,"username":"gmpolice","id":"21857067"},{"start":26,"end":38,"username":"EnvAgencyNW","id":"236338186"},{"start":39,"end":49,"username":"EnvAgency","id":"47331384"}],"annotations":{},"urls":{}},"referenced_tweets":[{"type":"replied_to","id":"1351983587608948737"}],"possibly_sensitive":false,"author_id":"1278018320550301698","public_metrics":{"retweet_count":1,"reply_count":1,"like_count":0,"quote_count":0},"id":"1351988856862765058","text":"@ManCityCouncil @gmpolice @EnvAgencyNW @EnvAgency Is it only certain parts of Northenden?","conversation_id":"1351983587608948737","in_reply_to_user_id":"26461381","context_annotations":{},"attachments":{"media_keys":{}}},{"source":"Twitter for Android","created_at":"2021-01-20T20:23:56.000Z","lang":"en","entities":{"hashtags":{},"mentions":[{"start":3,"end":13,"username":"helenpidd","id":"19000029"},{"start":89,"end":101,"username":"EnvAgencyNW","id":"236338186"}],"annotations":[{"start":48,"end":60,"probability":0.8874,"type":"Place","normalized_text":"West Didsbury"},{"start":66,"end":75,"probability":0.5932,"type":"Place","normalized_text":"Northenden"}],"urls":{}},"referenced_tweets":[{"type":"retweeted","id":"1351985810283909121"}],"possibly_sensitive":false,"author_id":"165790231","public_metrics":{"retweet_count":29,"reply_count":0,"like_count":0,"quote_count":0},"id":"1351988854476181504","text":"RT @helenpidd: Severe flood warnings issued for West Didsbury and Northenden meaning the @EnvAgencyNW thinks there’s a danger to life. http…","conversation_id":"1351988854476181504","context_annotations":{},"attachments":{"media_keys":{}}},{"source":"Twitter for iPhone","created_at":"2021-01-20T20:23:44.000Z","lang":"en","entities":{"hashtags":{},"mentions":[{"start":3,"end":16,"username":"EnvAgencyYNE","id":"222468030"}],"annotations":[{"start":111,"end":115,"probability":0.4164,"type":"Organization","normalized_text":"Covid"}],"urls":{}},"referenced_tweets":[{"type":"retweeted","id":"1351982164313825285"}],"possibly_sensitive":false,"author_id":"1237677006432743430","public_metrics":{"retweet_count":11,"reply_count":0,"like_count":0,"quote_count":0},"id":"1351988804467482624","text":"RT @EnvAgencyYNE: Our field team was in Old Denaby today putting up temporary barriers to ensure access to the Covid vaccination site is ma…","conversation_id":"1351988804467482624","context_annotations":[{"domain":{"id":"123","name":"Ongoing News Story","description":"Ongoing News Stories like 'Brexit'"},"entity":{"id":"1220701888179359745","name":"COVID-19"}}],"attachments":{"media_keys":{}}},{"source":"Twitter for iPhone","created_at":"2021-01-20T20:23:33.000Z","lang":"en","entities":{"hashtags":[{"start":41,"end":47,"tag":"flood"},{"start":60,"end":73,"tag":"EastDidsbury"},{"start":74,"end":87,"tag":"WestDidsbury"},{"start":92,"end":103,"tag":"Northenden"}],"mentions":[{"start":3,"end":15,"username":"EnvAgencyNW","id":"236338186"}],"annotations":{},"urls":{}},"referenced_tweets":[{"type":"retweeted","id":"1351983472181534720"}],"possibly_sensitive":false,"author_id":"62886371","public_metrics":{"retweet_count":77,"reply_count":0,"like_count":0,"quote_count":0},"id":"1351988757424205833","text":"RT @EnvAgencyNW: We have issued a severe #flood warning for #EastDidsbury #WestDidsbury and #Northenden which means a threat to life and si…","conversation_id":"1351988757424205833","context_annotations":{},"attachments":{"media_keys":{}}},{"source":"Twitter Web App","created_at":"2021-01-20T20:23:24.000Z","lang":"en","entities":{"hashtags":{},"mentions":[{"start":3,"end":13,"username":"helenpidd","id":"19000029"},{"start":89,"end":101,"username":"EnvAgencyNW","id":"236338186"}],"annotations":[{"start":48,"end":60,"probability":0.8874,"type":"Place","normalized_text":"West Didsbury"},{"start":66,"end":75,"probability":0.5932,"type":"Place","normalized_text":"Northenden"}],"urls":{}},"referenced_tweets":[{"type":"retweeted","id":"1351985810283909121"}],"possibly_sensitive":false,"author_id":"16910182","public_metrics":{"retweet_count":29,"reply_count":0,"like_count":0,"quote_count":0},"id":"1351988721063751683","text":"RT @helenpidd: Severe flood warnings issued for West Didsbury and Northenden meaning the @EnvAgencyNW thinks there’s a danger to life. http…","conversation_id":"1351988721063751683","context_annotations":{},"attachments":{"media_keys":{}}},{"source":"Twitter for iPhone","created_at":"2021-01-20T20:23:02.000Z","lang":"en","entities":{"hashtags":{},"mentions":[{"start":3,"end":16,"username":"EnvAgencyYNE","id":"222468030"}],"annotations":[{"start":81,"end":92,"probability":0.8179,"type":"Place","normalized_text":"Temple Manor"}],"urls":{}},"referenced_tweets":[{"type":"retweeted","id":"1351986378444328967"}],"possibly_sensitive":false,"author_id":"1237677006432743430","public_metrics":{"retweet_count":9,"reply_count":0,"like_count":0,"quote_count":0},"id":"1351988630034780160","text":"RT @EnvAgencyYNE: We have been bolstering the repairs we are currently making to Temple Manor wash lands in the Lower Aire today, as they f…","conversation_id":"1351988630034780160","context_annotations":{},"attachments":{"media_keys":{}}},{"source":"Twitter for iPhone","created_at":"2021-01-20T20:22:59.000Z","lang":"en","entities":{"hashtags":[{"start":41,"end":47,"tag":"flood"},{"start":60,"end":73,"tag":"EastDidsbury"},{"start":74,"end":87,"tag":"WestDidsbury"},{"start":92,"end":103,"tag":"Northenden"}],"mentions":[{"start":3,"end":15,"username":"EnvAgencyNW","id":"236338186"}],"annotations":{},"urls":{}},"referenced_tweets":[{"type":"retweeted","id":"1351983472181534720"}],"possibly_sensitive":false,"author_id":"298943932","public_metrics":{"retweet_count":77,"reply_count":0,"like_count":0,"quote_count":0},"id":"1351988616197795840","text":"RT @EnvAgencyNW: We have issued a severe #flood warning for #EastDidsbury #WestDidsbury and #Northenden which means a threat to life and si…","conversation_id":"1351988616197795840","context_annotations":{},"attachments":{"media_keys":{}}},{"source":"Twitter Web App","created_at":"2021-01-20T20:22:57.000Z","lang":"en","entities":{"hashtags":{},"mentions":[{"start":3,"end":15,"username":"MeganClinch","id":"1600886042"},{"start":17,"end":33,"username":"Tod_Flood_Group","id":"955596905769205762"},{"start":34,"end":45,"username":"Calderdale","id":"20065945"},{"start":46,"end":61,"username":"HalfpennyKerry","id":"705125940569968641"},{"start":62,"end":72,"username":"floodmary","id":"246324373"},{"start":73,"end":80,"username":"mrsk3r","id":"296174206"},{"start":81,"end":96,"username":"slowtheflow_UK","id":"738462567316770816"},{"start":97,"end":113,"username":"CalderdaleFound","id":"20770063"},{"start":114,"end":129,"username":"FloodDigitalEA","id":"913682914356994048"}],"annotations":{},"urls":{}},"referenced_tweets":[{"type":"retweeted","id":"1351983850277253123"}],"possibly_sensitive":false,"author_id":"149134489","public_metrics":{"retweet_count":2,"reply_count":0,"like_count":0,"quote_count":0},"id":"1351988607062593537","text":"RT @MeganClinch: @Tod_Flood_Group @Calderdale @HalfpennyKerry @floodmary @mrsk3r @slowtheflow_UK @CalderdaleFound @FloodDigitalEA @EnvAgenc…","conversation_id":"1351988607062593537","context_annotations":{},"attachments":{"media_keys":{}}},{"source":"Twitter for Android","created_at":"2021-01-20T20:22:51.000Z","lang":"en","entities":{"hashtags":[{"start":41,"end":47,"tag":"flood"},{"start":60,"end":73,"tag":"EastDidsbury"},{"start":74,"end":87,"tag":"WestDidsbury"},{"start":92,"end":103,"tag":"Northenden"}],"mentions":[{"start":3,"end":15,"username":"EnvAgencyNW","id":"236338186"}],"annotations":{},"urls":{}},"referenced_tweets":[{"type":"retweeted","id":"1351983472181534720"}],"possibly_sensitive":false,"author_id":"21520503","public_metrics":{"retweet_count":77,"reply_count":0,"like_count":0,"quote_count":0},"id":"1351988582509137921","text":"RT @EnvAgencyNW: We have issued a severe #flood warning for #EastDidsbury #WestDidsbury and #Northenden which means a threat to life and si…","conversation_id":"1351988582509137921","context_annotations":{},"attachments":{"media_keys":{}}},{"source":"Twitter for Android","created_at":"2021-01-20T20:22:45.000Z","lang":"en","entities":{"hashtags":{},"mentions":[{"start":3,"end":18,"username":"ManCityCouncil","id":"26461381"},{"start":23,"end":32,"username":"gmpolice","id":"21857067"},{"start":39,"end":51,"username":"EnvAgencyNW","id":"236338186"}],"annotations":[{"start":104,"end":111,"probability":0.9452,"type":"Place","normalized_text":"Didsbury"},{"start":114,"end":121,"probability":0.3086,"type":"Place","normalized_text":"Chorlton"},{"start":125,"end":134,"probability":0.3963,"type":"Place","normalized_text":"Northenden"}],"urls":{}},"referenced_tweets":[{"type":"retweeted","id":"1351983587608948737"}],"possibly_sensitive":false,"author_id":"165790231","public_metrics":{"retweet_count":176,"reply_count":0,"like_count":0,"quote_count":0},"id":"1351988557385261057","text":"RT @ManCityCouncil: ⚠️ @gmpolice &amp; @EnvAgencyNW have announced a Severe Flood Warning covering parts of Didsbury, Chorlton &amp; Northenden as…","conversation_id":"1351988557385261057","context_annotations":{},"attachments":{"media_keys":{}}},{"source":"Twitter for iPhone","created_at":"2021-01-20T20:22:42.000Z","lang":"en","entities":{"hashtags":{},"mentions":[{"start":3,"end":18,"username":"ManCityCouncil","id":"26461381"},{"start":23,"end":32,"username":"gmpolice","id":"21857067"},{"start":39,"end":51,"username":"EnvAgencyNW","id":"236338186"}],"annotations":[{"start":104,"end":111,"probability":0.9452,"type":"Place","normalized_text":"Didsbury"},{"start":114,"end":121,"probability":0.3086,"type":"Place","normalized_text":"Chorlton"},{"start":125,"end":134,"probability":0.3963,"type":"Place","normalized_text":"Northenden"}],"urls":{}},"referenced_tweets":[{"type":"retweeted","id":"1351983587608948737"}],"possibly_sensitive":false,"author_id":"18630487","public_metrics":{"retweet_count":176,"reply_count":0,"like_count":0,"quote_count":0},"id":"1351988546568073225","text":"RT @ManCityCouncil: ⚠️ @gmpolice &amp; @EnvAgencyNW have announced a Severe Flood Warning covering parts of Didsbury, Chorlton &amp; Northenden as…","conversation_id":"1351988546568073225","context_annotations":{},"attachments":{"media_keys":{}}},{"source":"Twitter Web App","created_at":"2021-01-20T20:22:24.000Z","lang":"en","entities":{"hashtags":[{"start":41,"end":47,"tag":"flood"},{"start":60,"end":73,"tag":"EastDidsbury"},{"start":74,"end":87,"tag":"WestDidsbury"},{"start":92,"end":103,"tag":"Northenden"}],"mentions":[{"start":3,"end":15,"username":"EnvAgencyNW","id":"236338186"}],"annotations":{},"urls":{}},"referenced_tweets":[{"type":"retweeted","id":"1351983472181534720"}],"possibly_sensitive":false,"author_id":"383286237","public_metrics":{"retweet_count":77,"reply_count":0,"like_count":0,"quote_count":0},"id":"1351988469644537862","text":"RT @EnvAgencyNW: We have issued a severe #flood warning for #EastDidsbury #WestDidsbury and #Northenden which means a threat to life and si…","conversation_id":"1351988469644537862","context_annotations":{},"attachments":{"media_keys":{}}},{"source":"Twitter for iPhone","created_at":"2021-01-20T20:22:18.000Z","lang":"en","entities":{"hashtags":{},"mentions":[{"start":3,"end":18,"username":"ManCityCouncil","id":"26461381"},{"start":23,"end":32,"username":"gmpolice","id":"21857067"},{"start":39,"end":51,"username":"EnvAgencyNW","id":"236338186"}],"annotations":[{"start":104,"end":111,"probability":0.9452,"type":"Place","normalized_text":"Didsbury"},{"start":114,"end":121,"probability":0.3086,"type":"Place","normalized_text":"Chorlton"},{"start":125,"end":134,"probability":0.3963,"type":"Place","normalized_text":"Northenden"}],"urls":{}},"referenced_tweets":[{"type":"retweeted","id":"1351983587608948737"}],"possibly_sensitive":false,"author_id":"2986384253","public_metrics":{"retweet_count":176,"reply_count":0,"like_count":0,"quote_count":0},"id":"1351988445175046153","text":"RT @ManCityCouncil: ⚠️ @gmpolice &amp; @EnvAgencyNW have announced a Severe Flood Warning covering parts of Didsbury, Chorlton &amp; Northenden as…","conversation_id":"1351988445175046153","context_annotations":{},"attachments":{"media_keys":{}}},{"source":"Twitter Web App","created_at":"2021-01-20T20:22:18.000Z","lang":"en","entities":{"hashtags":{},"mentions":[{"start":3,"end":18,"username":"ManCityCouncil","id":"26461381"},{"start":23,"end":32,"username":"gmpolice","id":"21857067"},{"start":39,"end":51,"username":"EnvAgencyNW","id":"236338186"}],"annotations":[{"start":104,"end":111,"probability":0.9452,"type":"Place","normalized_text":"Didsbury"},{"start":114,"end":121,"probability":0.3086,"type":"Place","normalized_text":"Chorlton"},{"start":125,"end":134,"probability":0.3963,"type":"Place","normalized_text":"Northenden"}],"urls":{}},"referenced_tweets":[{"type":"retweeted","id":"1351983587608948737"}],"possibly_sensitive":false,"author_id":"914225650940174337","public_metrics":{"retweet_count":176,"reply_count":0,"like_count":0,"quote_count":0},"id":"1351988443312746498","text":"RT @ManCityCouncil: ⚠️ @gmpolice &amp; @EnvAgencyNW have announced a Severe Flood Warning covering parts of Didsbury, Chorlton &amp; Northenden as…","conversation_id":"1351988443312746498","context_annotations":{},"attachments":{"media_keys":{}}},{"source":"Twitter for Android","created_at":"2021-01-20T20:22:13.000Z","lang":"en","entities":{"hashtags":{},"mentions":[{"start":3,"end":18,"username":"ManCityCouncil","id":"26461381"},{"start":23,"end":32,"username":"gmpolice","id":"21857067"},{"start":39,"end":51,"username":"EnvAgencyNW","id":"236338186"}],"annotations":[{"start":104,"end":111,"probability":0.9452,"type":"Place","normalized_text":"Didsbury"},{"start":114,"end":121,"probability":0.3086,"type":"Place","normalized_text":"Chorlton"},{"start":125,"end":134,"probability":0.3963,"type":"Place","normalized_text":"Northenden"}],"urls":{}},"referenced_tweets":[{"type":"retweeted","id":"1351983587608948737"}],"possibly_sensitive":false,"author_id":"3369258166","public_metrics":{"retweet_count":176,"reply_count":0,"like_count":0,"quote_count":0},"id":"1351988424010563584","text":"RT @ManCityCouncil: ⚠️ @gmpolice &amp; @EnvAgencyNW have announced a Severe Flood Warning covering parts of Didsbury, Chorlton &amp; Northenden as…","conversation_id":"1351988424010563584","context_annotations":{},"attachments":{"media_keys":{}}},{"source":"Twitter for iPhone","created_at":"2021-01-20T20:22:13.000Z","lang":"sv","entities":{"hashtags":{},"mentions":[{"start":0,"end":11,"username":"_PrinceAco","id":"1321822980444508165"},{"start":12,"end":24,"username":"EnvAgencyNW","id":"236338186"},{"start":25,"end":35,"username":"EnvAgency","id":"47331384"}],"annotations":{},"urls":{}},"referenced_tweets":[{"type":"replied_to","id":"1351987903442911248"}],"possibly_sensitive":false,"author_id":"58200643","public_metrics":{"retweet_count":0,"reply_count":0,"like_count":1,"quote_count":0},"id":"1351988423213637633","text":"@_PrinceAco @EnvAgencyNW @EnvAgency Idiot","conversation_id":"1351983472181534720","in_reply_to_user_id":"1321822980444508165","context_annotations":{},"attachments":{"media_keys":{}}},{"source":"Twitter Web App","created_at":"2021-01-20T20:21:48.000Z","lang":"en","entities":{"hashtags":{},"mentions":[{"start":3,"end":12,"username":"MayorRos","id":"1096805563"}],"annotations":{},"urls":{}},"referenced_tweets":[{"type":"retweeted","id":"1351986570522472448"}],"possibly_sensitive":false,"author_id":"255948648","public_metrics":{"retweet_count":5,"reply_count":0,"like_count":0,"quote_count":0},"id":"1351988320230903809","text":"RT @MayorRos: I would like to thank all our staff and partner agencies for everything they have done &amp; continue to do. We're preparing for…","conversation_id":"1351988320230903809","context_annotations":{},"attachments":{"media_keys":{}}},{"source":"Twitter for Android","created_at":"2021-01-20T20:21:44.000Z","lang":"en","entities":{"hashtags":{},"mentions":[{"start":3,"end":18,"username":"ManCityCouncil","id":"26461381"},{"start":23,"end":32,"username":"gmpolice","id":"21857067"},{"start":39,"end":51,"username":"EnvAgencyNW","id":"236338186"}],"annotations":[{"start":104,"end":111,"probability":0.9452,"type":"Place","normalized_text":"Didsbury"},{"start":114,"end":121,"probability":0.3086,"type":"Place","normalized_text":"Chorlton"},{"start":125,"end":134,"probability":0.3963,"type":"Place","normalized_text":"Northenden"}],"urls":{}},"referenced_tweets":[{"type":"retweeted","id":"1351983587608948737"}],"possibly_sensitive":false,"author_id":"2364873847","public_metrics":{"retweet_count":176,"reply_count":0,"like_count":0,"quote_count":0},"id":"1351988302899982342","text":"RT @ManCityCouncil: ⚠️ @gmpolice &amp; @EnvAgencyNW have announced a Severe Flood Warning covering parts of Didsbury, Chorlton &amp; Northenden as…","conversation_id":"1351988302899982342","context_annotations":{},"attachments":{"media_keys":{}}},{"source":"Twitter for iPhone","created_at":"2021-01-20T20:21:30.000Z","lang":"en","entities":{"hashtags":{},"mentions":[{"start":3,"end":12,"username":"MayorRos","id":"1096805563"}],"annotations":{},"urls":{}},"referenced_tweets":[{"type":"retweeted","id":"1351986570522472448"}],"possibly_sensitive":false,"author_id":"792099690103840769","public_metrics":{"retweet_count":5,"reply_count":0,"like_count":0,"quote_count":0},"id":"1351988241264758786","text":"RT @MayorRos: I would like to thank all our staff and partner agencies for everything they have done &amp; continue to do. We're preparing for…","conversation_id":"1351988241264758786","context_annotations":{},"attachments":{"media_keys":{}}},{"source":"Twitter Web App","created_at":"2021-01-20T20:21:06.000Z","lang":"en","entities":{"hashtags":{},"mentions":[{"start":3,"end":16,"username":"OfficialWXUK","id":"1215834974919766016"},{"start":68,"end":78,"username":"EnvAgency","id":"47331384"}],"annotations":[{"start":98,"end":110,"probability":0.8692,"type":"Place","normalized_text":"East Didsbury"}],"urls":{}},"referenced_tweets":[{"type":"retweeted","id":"1351985740704579585"}],"possibly_sensitive":false,"author_id":"1293805060980445186","public_metrics":{"retweet_count":4,"reply_count":0,"like_count":0,"quote_count":0},"id":"1351988142459539456","text":"RT @OfficialWXUK: Two SEVERE FLOOD WARNINGS have been issued by the @EnvAgency\n\n— River Mersey at East Didsbury\n— River Mersey at West Dids…","conversation_id":"1351988142459539456","context_annotations":{},"attachments":{"media_keys":{}}},{"source":"Twitter for iPhone","created_at":"2021-01-20T20:20:57.000Z","lang":"en","entities":{"hashtags":{},"mentions":[{"start":3,"end":13,"username":"helenpidd","id":"19000029"},{"start":89,"end":101,"username":"EnvAgencyNW","id":"236338186"}],"annotations":[{"start":48,"end":60,"probability":0.8874,"type":"Place","normalized_text":"West Didsbury"},{"start":66,"end":75,"probability":0.5932,"type":"Place","normalized_text":"Northenden"}],"urls":{}},"referenced_tweets":[{"type":"retweeted","id":"1351985810283909121"}],"possibly_sensitive":false,"author_id":"580732588","public_metrics":{"retweet_count":29,"reply_count":0,"like_count":0,"quote_count":0},"id":"1351988105339949057","text":"RT @helenpidd: Severe flood warnings issued for West Didsbury and Northenden meaning the @EnvAgencyNW thinks there’s a danger to life. http…","conversation_id":"1351988105339949057","context_annotations":{},"attachments":{"media_keys":{}}},{"source":"Twitter Web App","created_at":"2021-01-20T20:20:40.000Z","lang":"en","entities":{"hashtags":[{"start":41,"end":47,"tag":"flood"},{"start":60,"end":73,"tag":"EastDidsbury"},{"start":74,"end":87,"tag":"WestDidsbury"},{"start":92,"end":103,"tag":"Northenden"}],"mentions":[{"start":3,"end":15,"username":"EnvAgencyNW","id":"236338186"}],"annotations":{},"urls":{}},"referenced_tweets":[{"type":"retweeted","id":"1351983472181534720"}],"possibly_sensitive":false,"author_id":"914225650940174337","public_metrics":{"retweet_count":77,"reply_count":0,"like_count":0,"quote_count":0},"id":"1351988034154147840","text":"RT @EnvAgencyNW: We have issued a severe #flood warning for #EastDidsbury #WestDidsbury and #Northenden which means a threat to life and si…","conversation_id":"1351988034154147840","context_annotations":{},"attachments":{"media_keys":{}}},{"source":"Twitter for iPad","created_at":"2021-01-20T20:20:28.000Z","lang":"en","entities":{"hashtags":{},"mentions":[{"start":3,"end":13,"username":"helenpidd","id":"19000029"},{"start":89,"end":101,"username":"EnvAgencyNW","id":"236338186"}],"annotations":[{"start":48,"end":60,"probability":0.8874,"type":"Place","normalized_text":"West Didsbury"},{"start":66,"end":75,"probability":0.5932,"type":"Place","normalized_text":"Northenden"}],"urls":{}},"referenced_tweets":[{"type":"retweeted","id":"1351985810283909121"}],"possibly_sensitive":false,"author_id":"143779403","public_metrics":{"retweet_count":29,"reply_count":0,"like_count":0,"quote_count":0},"id":"1351987983256326147","text":"RT @helenpidd: Severe flood warnings issued for West Didsbury and Northenden meaning the @EnvAgencyNW thinks there’s a danger to life. http…","conversation_id":"1351987983256326147","context_annotations":[{"domain":{"id":"10","name":"Person","description":"Named people in the world like Nelson Mandela"},"entity":{"id":"1070735188836081664","name":"Andy Burnham","description":"British politician"}},{"domain":{"id":"35","name":"Politician","description":"Politicians in the world, like Joe Biden"},"entity":{"id":"1070735188836081664","name":"Andy Burnham","description":"British politician"}}],"attachments":{"media_keys":{}}},{"source":"TweetDeck","created_at":"2021-01-20T20:20:16.000Z","lang":"en","entities":{"hashtags":[{"start":41,"end":47,"tag":"flood"},{"start":60,"end":73,"tag":"EastDidsbury"},{"start":74,"end":87,"tag":"WestDidsbury"},{"start":92,"end":103,"tag":"Northenden"}],"mentions":[{"start":3,"end":15,"username":"EnvAgencyNW","id":"236338186"}],"annotations":{},"urls":{}},"referenced_tweets":[{"type":"retweeted","id":"1351983472181534720"}],"possibly_sensitive":false,"author_id":"64683174","public_metrics":{"retweet_count":77,"reply_count":0,"like_count":0,"quote_count":0},"id":"1351987934073933836","text":"RT @EnvAgencyNW: We have issued a severe #flood warning for #EastDidsbury #WestDidsbury and #Northenden which means a threat to life and si…","conversation_id":"1351987934073933836","context_annotations":{},"attachments":{"media_keys":{}}},{"source":"Twitter for iPhone","created_at":"2021-01-20T20:20:14.000Z","lang":"en","entities":{"hashtags":[{"start":41,"end":47,"tag":"flood"},{"start":60,"end":73,"tag":"EastDidsbury"},{"start":74,"end":87,"tag":"WestDidsbury"},{"start":92,"end":103,"tag":"Northenden"}],"mentions":[{"start":3,"end":15,"username":"EnvAgencyNW","id":"236338186"}],"annotations":{},"urls":{}},"referenced_tweets":[{"type":"retweeted","id":"1351983472181534720"}],"possibly_sensitive":false,"author_id":"1135144364","public_metrics":{"retweet_count":77,"reply_count":0,"like_count":0,"quote_count":0},"id":"1351987922472468483","text":"RT @EnvAgencyNW: We have issued a severe #flood warning for #EastDidsbury #WestDidsbury and #Northenden which means a threat to life and si…","conversation_id":"1351987922472468483","context_annotations":{},"attachments":{"media_keys":{}}},{"source":"Twitter for Android","created_at":"2021-01-20T20:20:11.000Z","lang":"en","entities":{"hashtags":[{"start":41,"end":47,"tag":"flood"},{"start":60,"end":73,"tag":"EastDidsbury"},{"start":74,"end":87,"tag":"WestDidsbury"},{"start":92,"end":103,"tag":"Northenden"}],"mentions":[{"start":3,"end":15,"username":"EnvAgencyNW","id":"236338186"}],"annotations":{},"urls":{}},"referenced_tweets":[{"type":"retweeted","id":"1351983472181534720"}],"possibly_sensitive":false,"author_id":"1321822980444508165","public_metrics":{"retweet_count":77,"reply_count":0,"like_count":0,"quote_count":0},"id":"1351987911957377030","text":"RT @EnvAgencyNW: We have issued a severe #flood warning for #EastDidsbury #WestDidsbury and #Northenden which means a threat to life and si…","conversation_id":"1351987911957377030","context_annotations":{},"attachments":{"media_keys":{}}},{"source":"Twitter for iPhone","created_at":"2021-01-20T20:20:00.000Z","lang":"en","entities":{"hashtags":[{"start":68,"end":77,"tag":"Didsbury"}],"mentions":[{"start":3,"end":17,"username":"ElectricityNW","id":"335825728"}],"annotations":[{"start":50,"end":63,"probability":0.6564,"type":"Place","normalized_text":"Palentine Road"}],"urls":{}},"referenced_tweets":[{"type":"retweeted","id":"1351976153532264457"}],"possibly_sensitive":false,"author_id":"20147684","public_metrics":{"retweet_count":4,"reply_count":0,"like_count":0,"quote_count":0},"id":"1351987864188444673","text":"RT @ElectricityNW: Our engineers have been out to Palentine Road in #Didsbury earlier today to add sandbags around our substation to protec…","conversation_id":"1351987864188444673","context_annotations":{},"attachments":{"media_keys":{}}},{"source":"Twitter for iPhone","created_at":"2021-01-20T20:19:49.000Z","lang":"en","entities":{"hashtags":{},"mentions":[{"start":3,"end":13,"username":"helenpidd","id":"19000029"},{"start":89,"end":101,"username":"EnvAgencyNW","id":"236338186"}],"annotations":[{"start":48,"end":60,"probability":0.8874,"type":"Place","normalized_text":"West Didsbury"},{"start":66,"end":75,"probability":0.5932,"type":"Place","normalized_text":"Northenden"}],"urls":{}},"referenced_tweets":[{"type":"retweeted","id":"1351985810283909121"}],"possibly_sensitive":false,"author_id":"25501580","public_metrics":{"retweet_count":29,"reply_count":0,"like_count":0,"quote_count":0},"id":"1351987818508263431","text":"RT @helenpidd: Severe flood warnings issued for West Didsbury and Northenden meaning the @EnvAgencyNW thinks there’s a danger to life. http…","conversation_id":"1351987818508263431","context_annotations":{},"attachments":{"media_keys":{}}},{"source":"Twitter for Android","created_at":"2021-01-20T20:19:47.000Z","lang":"en","entities":{"hashtags":[{"start":41,"end":47,"tag":"flood"},{"start":60,"end":73,"tag":"EastDidsbury"},{"start":74,"end":87,"tag":"WestDidsbury"},{"start":92,"end":103,"tag":"Northenden"}],"mentions":[{"start":3,"end":15,"username":"EnvAgencyNW","id":"236338186"}],"annotations":{},"urls":{}},"referenced_tweets":[{"type":"retweeted","id":"1351983472181534720"}],"possibly_sensitive":false,"author_id":"1112038022927863808","public_metrics":{"retweet_count":77,"reply_count":0,"like_count":0,"quote_count":0},"id":"1351987810727813122","text":"RT @EnvAgencyNW: We have issued a severe #flood warning for #EastDidsbury #WestDidsbury and #Northenden which means a threat to life and si…","conversation_id":"1351987810727813122","context_annotations":{},"attachments":{"media_keys":{}}},{"source":"Twitter for Android","created_at":"2021-01-20T20:18:47.000Z","lang":"en","entities":{"hashtags":{},"mentions":[{"start":3,"end":16,"username":"EnvAgencyYNE","id":"222468030"}],"annotations":[{"start":81,"end":92,"probability":0.8179,"type":"Place","normalized_text":"Temple Manor"}],"urls":{}},"referenced_tweets":[{"type":"retweeted","id":"1351986378444328967"}],"possibly_sensitive":false,"author_id":"1057342818","public_metrics":{"retweet_count":9,"reply_count":0,"like_count":0,"quote_count":0},"id":"1351987559799386116","text":"RT @EnvAgencyYNE: We have been bolstering the repairs we are currently making to Temple Manor wash lands in the Lower Aire today, as they f…","conversation_id":"1351987559799386116","context_annotations":{},"attachments":{"media_keys":{}}},{"source":"Twitter for iPhone","created_at":"2021-01-20T20:18:38.000Z","lang":"en","entities":{"hashtags":[{"start":41,"end":47,"tag":"flood"},{"start":60,"end":73,"tag":"EastDidsbury"},{"start":74,"end":87,"tag":"WestDidsbury"},{"start":92,"end":103,"tag":"Northenden"}],"mentions":[{"start":3,"end":15,"username":"EnvAgencyNW","id":"236338186"}],"annotations":{},"urls":{}},"referenced_tweets":[{"type":"retweeted","id":"1351983472181534720"}],"possibly_sensitive":false,"author_id":"21489823","public_metrics":{"retweet_count":77,"reply_count":0,"like_count":0,"quote_count":0},"id":"1351987523610882050","text":"RT @EnvAgencyNW: We have issued a severe #flood warning for #EastDidsbury #WestDidsbury and #Northenden which means a threat to life and si…","conversation_id":"1351987523610882050","context_annotations":{},"attachments":{"media_keys":{}}},{"source":"Twitter for Android","created_at":"2021-01-20T20:18:28.000Z","lang":"en","entities":{"hashtags":{},"mentions":[{"start":3,"end":18,"username":"ManCityCouncil","id":"26461381"},{"start":23,"end":32,"username":"gmpolice","id":"21857067"},{"start":39,"end":51,"username":"EnvAgencyNW","id":"236338186"}],"annotations":[{"start":104,"end":111,"probability":0.9452,"type":"Place","normalized_text":"Didsbury"},{"start":114,"end":121,"probability":0.3086,"type":"Place","normalized_text":"Chorlton"},{"start":125,"end":134,"probability":0.3963,"type":"Place","normalized_text":"Northenden"}],"urls":{}},"referenced_tweets":[{"type":"retweeted","id":"1351983587608948737"}],"possibly_sensitive":false,"author_id":"219994059","public_metrics":{"retweet_count":176,"reply_count":0,"like_count":0,"quote_count":0},"id":"1351987477574279181","text":"RT @ManCityCouncil: ⚠️ @gmpolice &amp; @EnvAgencyNW have announced a Severe Flood Warning covering parts of Didsbury, Chorlton &amp; Northenden as…","conversation_id":"1351987477574279181","context_annotations":{},"attachments":{"media_keys":{}}},{"source":"Twitter for iPhone","created_at":"2021-01-20T20:17:55.000Z","lang":"en","entities":{"hashtags":[{"start":41,"end":47,"tag":"flood"},{"start":60,"end":73,"tag":"EastDidsbury"},{"start":74,"end":87,"tag":"WestDidsbury"},{"start":92,"end":103,"tag":"Northenden"}],"mentions":[{"start":3,"end":15,"username":"EnvAgencyNW","id":"236338186"}],"annotations":{},"urls":{}},"referenced_tweets":[{"type":"retweeted","id":"1351983472181534720"}],"possibly_sensitive":false,"author_id":"236972383","public_metrics":{"retweet_count":77,"reply_count":0,"like_count":0,"quote_count":0},"id":"1351987339950698498","text":"RT @EnvAgencyNW: We have issued a severe #flood warning for #EastDidsbury #WestDidsbury and #Northenden which means a threat to life and si…","conversation_id":"1351987339950698498","context_annotations":{},"attachments":{"media_keys":{}}},{"source":"Twitter Web App","created_at":"2021-01-20T20:17:47.000Z","lang":"en","entities":{"hashtags":[{"start":41,"end":47,"tag":"flood"},{"start":60,"end":73,"tag":"EastDidsbury"},{"start":74,"end":87,"tag":"WestDidsbury"},{"start":92,"end":103,"tag":"Northenden"}],"mentions":[{"start":3,"end":15,"username":"EnvAgencyNW","id":"236338186"}],"annotations":{},"urls":{}},"referenced_tweets":[{"type":"retweeted","id":"1351983472181534720"}],"possibly_sensitive":false,"author_id":"47331384","public_metrics":{"retweet_count":77,"reply_count":0,"like_count":0,"quote_count":0},"id":"1351987307008708611","text":"RT @EnvAgencyNW: We have issued a severe #flood warning for #EastDidsbury #WestDidsbury and #Northenden which means a threat to life and si…","conversation_id":"1351987307008708611","context_annotations":{},"attachments":{"media_keys":{}}},{"source":"Twitter for iPhone","created_at":"2021-01-20T20:17:43.000Z","lang":"en","entities":{"hashtags":{},"mentions":[{"start":3,"end":18,"username":"ManCityCouncil","id":"26461381"},{"start":23,"end":32,"username":"gmpolice","id":"21857067"},{"start":39,"end":51,"username":"EnvAgencyNW","id":"236338186"}],"annotations":[{"start":104,"end":111,"probability":0.9452,"type":"Place","normalized_text":"Didsbury"},{"start":114,"end":121,"probability":0.3086,"type":"Place","normalized_text":"Chorlton"},{"start":125,"end":134,"probability":0.3963,"type":"Place","normalized_text":"Northenden"}],"urls":{}},"referenced_tweets":[{"type":"retweeted","id":"1351983587608948737"}],"possibly_sensitive":false,"author_id":"906074455402844160","public_metrics":{"retweet_count":176,"reply_count":0,"like_count":0,"quote_count":0},"id":"1351987292865486858","text":"RT @ManCityCouncil: ⚠️ @gmpolice &amp; @EnvAgencyNW have announced a Severe Flood Warning covering parts of Didsbury, Chorlton &amp; Northenden as…","conversation_id":"1351987292865486858","context_annotations":{},"attachments":{"media_keys":{}}},{"source":"Twitter for iPhone","created_at":"2021-01-20T20:17:43.000Z","lang":"en","entities":{"hashtags":[{"start":41,"end":47,"tag":"flood"},{"start":60,"end":73,"tag":"EastDidsbury"},{"start":74,"end":87,"tag":"WestDidsbury"},{"start":92,"end":103,"tag":"Northenden"}],"mentions":[{"start":3,"end":15,"username":"EnvAgencyNW","id":"236338186"}],"annotations":{},"urls":{}},"referenced_tweets":[{"type":"retweeted","id":"1351983472181534720"}],"possibly_sensitive":false,"author_id":"858844932","public_metrics":{"retweet_count":77,"reply_count":0,"like_count":0,"quote_count":0},"id":"1351987291921776640","text":"RT @EnvAgencyNW: We have issued a severe #flood warning for #EastDidsbury #WestDidsbury and #Northenden which means a threat to life and si…","conversation_id":"1351987291921776640","context_annotations":{},"attachments":{"media_keys":{}}},{"source":"Twitter for Android","created_at":"2021-01-20T20:17:20.000Z","lang":"en","entities":{"hashtags":{},"mentions":[{"start":57,"end":73,"username":"unitedutilities","id":"20982364"},{"start":154,"end":167,"username":"CheshireEast","id":"205636848"},{"start":173,"end":183,"username":"EnvAgency","id":"47331384"}],"annotations":{},"urls":[{"start":244,"end":267,"url":"https://t.co/GR77KqhaDt","expanded_url":"https://twitter.com/eroomal/status/1351987194559426562/photo/1","display_url":"pic.twitter.com/GR77KqhaDt"}]},"referenced_tweets":{},"possibly_sensitive":false,"author_id":"2688332234","public_metrics":{"retweet_count":0,"reply_count":2,"like_count":0,"quote_count":0},"id":"1351987194559426562","text":"The drains are overflowing,\nThere's sewage on the floor,\n@unitedutilities are ignoring us...\nSo Prosecco we must pour! \n🙈🙈🙈🙈🙈🙈🙈🙈\n\nAlso looking sternly at @CheshireEast  and @EnvAgency I have a baby, and sewage is leaking onto my kitchen floor. https://t.co/GR77KqhaDt","conversation_id":"1351987194559426562","context_annotations":[{"domain":{"id":"65","name":"Interests and Hobbies Vertical","description":"Top level interests and hobbies groupings, like Food or Travel"},"entity":{"id":"825047692124442624","name":"Food","description":"Food"}},{"domain":{"id":"65","name":"Interests and Hobbies Vertical","description":"Top level interests and hobbies groupings, like Food or Travel"},"entity":{"id":"834828264786898945","name":"Drinks","description":"Drinks"}},{"domain":{"id":"66","name":"Interests and Hobbies Category","description":"A grouping of interests and hobbies entities, like Novelty Food or Destinations"},"entity":{"id":"834828445238431744","name":"Generic Drinks","description":"Generic Drinks"}},{"domain":{"id":"67","name":"Interests and Hobbies","description":"Interests, opinions, and behaviors of individuals, groups, or cultures; like Speciality Cooking or Theme Parks"},"entity":{"id":"850145694807498752","name":"Prosecco","description":"Prosecco"}}],"attachments":{"media_keys":["3_1351987191170400258"]}},{"source":"Twitter for iPad","created_at":"2021-01-20T20:17:14.000Z","lang":"en","entities":{"hashtags":{},"mentions":[{"start":0,"end":13,"username":"SheffCouncil","id":"41626220"},{"start":14,"end":27,"username":"TravelSYorks","id":"19072999"},{"start":28,"end":41,"username":"BBCSheffield","id":"279001916"},{"start":42,"end":54,"username":"katejosephs","id":"206881266"},{"start":55,"end":71,"username":"sccstreetsahead","id":"703697258"},{"start":72,"end":88,"username":"sheffcitycentre","id":"222063355"},{"start":89,"end":102,"username":"EnvAgencyYNE","id":"222468030"}],"annotations":{},"urls":{}},"referenced_tweets":[{"type":"replied_to","id":"1351824251368693765"}],"possibly_sensitive":false,"author_id":"534623514","public_metrics":{"retweet_count":0,"reply_count":0,"like_count":0,"quote_count":0},"id":"1351987170886774786","text":"@SheffCouncil @TravelSYorks @BBCSheffield @katejosephs @sccstreetsahead @sheffcitycentre @EnvAgencyYNE Looks like Phlegm is sinking","conversation_id":"1351824251368693765","in_reply_to_user_id":"41626220","context_annotations":{},"attachments":{"media_keys":{}}},{"source":"Twitter for iPhone","created_at":"2021-01-20T20:16:57.000Z","lang":"en","entities":{"hashtags":{},"mentions":[{"start":3,"end":18,"username":"ManCityCouncil","id":"26461381"},{"start":23,"end":32,"username":"gmpolice","id":"21857067"},{"start":39,"end":51,"username":"EnvAgencyNW","id":"236338186"}],"annotations":[{"start":104,"end":111,"probability":0.9452,"type":"Place","normalized_text":"Didsbury"},{"start":114,"end":121,"probability":0.3086,"type":"Place","normalized_text":"Chorlton"},{"start":125,"end":134,"probability":0.3963,"type":"Place","normalized_text":"Northenden"}],"urls":{}},"referenced_tweets":[{"type":"retweeted","id":"1351983587608948737"}],"possibly_sensitive":false,"author_id":"3772123109","public_metrics":{"retweet_count":176,"reply_count":0,"like_count":0,"quote_count":0},"id":"1351987097612267523","text":"RT @ManCityCouncil: ⚠️ @gmpolice &amp; @EnvAgencyNW have announced a Severe Flood Warning covering parts of Didsbury, Chorlton &amp; Northenden as…","conversation_id":"1351987097612267523","context_annotations":{},"attachments":{"media_keys":{}}},{"source":"Twitter for iPhone","created_at":"2021-01-20T20:16:55.000Z","lang":"en","entities":{"hashtags":{},"mentions":[{"start":3,"end":18,"username":"ManCityCouncil","id":"26461381"},{"start":23,"end":32,"username":"gmpolice","id":"21857067"},{"start":39,"end":51,"username":"EnvAgencyNW","id":"236338186"}],"annotations":[{"start":104,"end":111,"probability":0.9452,"type":"Place","normalized_text":"Didsbury"},{"start":114,"end":121,"probability":0.3086,"type":"Place","normalized_text":"Chorlton"},{"start":125,"end":134,"probability":0.3963,"type":"Place","normalized_text":"Northenden"}],"urls":{}},"referenced_tweets":[{"type":"retweeted","id":"1351983587608948737"}],"possibly_sensitive":false,"author_id":"741982874619023360","public_metrics":{"retweet_count":176,"reply_count":0,"like_count":0,"quote_count":0},"id":"1351987088032411657","text":"RT @ManCityCouncil: ⚠️ @gmpolice &amp; @EnvAgencyNW have announced a Severe Flood Warning covering parts of Didsbury, Chorlton &amp; Northenden as…","conversation_id":"1351987088032411657","context_annotations":{},"attachments":{"media_keys":{}}},{"source":"Twitter for Android","created_at":"2021-01-20T20:16:51.000Z","lang":"en","entities":{"hashtags":{},"mentions":[{"start":3,"end":18,"username":"ManCityCouncil","id":"26461381"},{"start":23,"end":32,"username":"gmpolice","id":"21857067"},{"start":39,"end":51,"username":"EnvAgencyNW","id":"236338186"}],"annotations":[{"start":104,"end":111,"probability":0.9452,"type":"Place","normalized_text":"Didsbury"},{"start":114,"end":121,"probability":0.3086,"type":"Place","normalized_text":"Chorlton"},{"start":125,"end":134,"probability":0.3963,"type":"Place","normalized_text":"Northenden"}],"urls":{}},"referenced_tweets":[{"type":"retweeted","id":"1351983587608948737"}],"possibly_sensitive":false,"author_id":"576934471","public_metrics":{"retweet_count":176,"reply_count":0,"like_count":0,"quote_count":0},"id":"1351987074191261696","text":"RT @ManCityCouncil: ⚠️ @gmpolice &amp; @EnvAgencyNW have announced a Severe Flood Warning covering parts of Didsbury, Chorlton &amp; Northenden as…","conversation_id":"1351987074191261696","context_annotations":{},"attachments":{"media_keys":{}}},{"source":"Twitter for Android","created_at":"2021-01-20T20:16:20.000Z","lang":"en","entities":{"hashtags":[{"start":41,"end":47,"tag":"flood"},{"start":60,"end":73,"tag":"EastDidsbury"},{"start":74,"end":87,"tag":"WestDidsbury"},{"start":92,"end":103,"tag":"Northenden"}],"mentions":[{"start":3,"end":15,"username":"EnvAgencyNW","id":"236338186"}],"annotations":{},"urls":{}},"referenced_tweets":[{"type":"retweeted","id":"1351983472181534720"}],"possibly_sensitive":false,"author_id":"2531521107","public_metrics":{"retweet_count":77,"reply_count":0,"like_count":0,"quote_count":0},"id":"1351986941651275778","text":"RT @EnvAgencyNW: We have issued a severe #flood warning for #EastDidsbury #WestDidsbury and #Northenden which means a threat to life and si…","conversation_id":"1351986941651275778","context_annotations":{},"attachments":{"media_keys":{}}},{"source":"Twitter Web App","created_at":"2021-01-20T20:16:11.000Z","lang":"en","entities":{"hashtags":{},"mentions":[{"start":3,"end":13,"username":"helenpidd","id":"19000029"},{"start":89,"end":101,"username":"EnvAgencyNW","id":"236338186"}],"annotations":[{"start":48,"end":60,"probability":0.8874,"type":"Place","normalized_text":"West Didsbury"},{"start":66,"end":75,"probability":0.5932,"type":"Place","normalized_text":"Northenden"}],"urls":{}},"referenced_tweets":[{"type":"retweeted","id":"1351985810283909121"}],"possibly_sensitive":false,"author_id":"1266488309674659842","public_metrics":{"retweet_count":29,"reply_count":0,"like_count":0,"quote_count":0},"id":"1351986903046885378","text":"RT @helenpidd: Severe flood warnings issued for West Didsbury and Northenden meaning the @EnvAgencyNW thinks there’s a danger to life. http…","conversation_id":"1351986903046885378","context_annotations":{},"attachments":{"media_keys":{}}},{"source":"Twitter for iPhone","created_at":"2021-01-20T20:16:03.000Z","lang":"en","entities":{"hashtags":[{"start":41,"end":47,"tag":"flood"},{"start":60,"end":73,"tag":"EastDidsbury"},{"start":74,"end":87,"tag":"WestDidsbury"},{"start":92,"end":103,"tag":"Northenden"}],"mentions":[{"start":3,"end":15,"username":"EnvAgencyNW","id":"236338186"}],"annotations":{},"urls":{}},"referenced_tweets":[{"type":"retweeted","id":"1351983472181534720"}],"possibly_sensitive":false,"author_id":"502754480","public_metrics":{"retweet_count":77,"reply_count":0,"like_count":0,"quote_count":0},"id":"1351986870343897089","text":"RT @EnvAgencyNW: We have issued a severe #flood warning for #EastDidsbury #WestDidsbury and #Northenden which means a threat to life and si…","conversation_id":"1351986870343897089","context_annotations":{},"attachments":{"media_keys":{}}},{"source":"Twitter for iPhone","created_at":"2021-01-20T20:15:57.000Z","lang":"en","entities":{"hashtags":[{"start":41,"end":47,"tag":"flood"},{"start":60,"end":73,"tag":"EastDidsbury"},{"start":74,"end":87,"tag":"WestDidsbury"},{"start":92,"end":103,"tag":"Northenden"}],"mentions":[{"start":3,"end":15,"username":"EnvAgencyNW","id":"236338186"}],"annotations":{},"urls":{}},"referenced_tweets":[{"type":"retweeted","id":"1351983472181534720"}],"possibly_sensitive":false,"author_id":"818183018","public_metrics":{"retweet_count":77,"reply_count":0,"like_count":0,"quote_count":0},"id":"1351986845241004032","text":"RT @EnvAgencyNW: We have issued a severe #flood warning for #EastDidsbury #WestDidsbury and #Northenden which means a threat to life and si…","conversation_id":"1351986845241004032","context_annotations":{},"attachments":{"media_keys":{}}},{"source":"Twitter for Android","created_at":"2021-01-20T20:15:49.000Z","lang":"en","entities":{"hashtags":[{"start":41,"end":47,"tag":"flood"},{"start":60,"end":73,"tag":"EastDidsbury"},{"start":74,"end":87,"tag":"WestDidsbury"},{"start":92,"end":103,"tag":"Northenden"}],"mentions":[{"start":3,"end":15,"username":"EnvAgencyNW","id":"236338186"}],"annotations":{},"urls":{}},"referenced_tweets":[{"type":"retweeted","id":"1351983472181534720"}],"possibly_sensitive":false,"author_id":"570321279","public_metrics":{"retweet_count":77,"reply_count":0,"like_count":0,"quote_count":0},"id":"1351986812688998400","text":"RT @EnvAgencyNW: We have issued a severe #flood warning for #EastDidsbury #WestDidsbury and #Northenden which means a threat to life and si…","conversation_id":"1351986812688998400","context_annotations":{},"attachments":{"media_keys":{}}},{"source":"Twitter for iPad","created_at":"2021-01-20T20:15:18.000Z","lang":"en","entities":{"hashtags":{},"mentions":[{"start":0,"end":10,"username":"helenpidd","id":"19000029"},{"start":11,"end":23,"username":"EnvAgencyNW","id":"236338186"}],"annotations":[{"start":63,"end":70,"probability":0.9325,"type":"Place","normalized_text":"Didsbury"}],"urls":{}},"referenced_tweets":[{"type":"replied_to","id":"1351985810283909121"}],"possibly_sensitive":false,"author_id":"1176463956862521345","public_metrics":{"retweet_count":1,"reply_count":0,"like_count":1,"quote_count":0},"id":"1351986684083249152","text":"@helenpidd @EnvAgencyNW Golly, I’ve never heard of flooding in Didsbury before! 😳","conversation_id":"1351985810283909121","in_reply_to_user_id":"19000029","context_annotations":{},"attachments":{"media_keys":{}}},{"source":"Twitter Web App","created_at":"2021-01-20T20:15:15.000Z","lang":"en","entities":{"hashtags":{},"mentions":[{"start":3,"end":13,"username":"helenpidd","id":"19000029"},{"start":89,"end":101,"username":"EnvAgencyNW","id":"236338186"}],"annotations":[{"start":48,"end":60,"probability":0.8874,"type":"Place","normalized_text":"West Didsbury"},{"start":66,"end":75,"probability":0.5932,"type":"Place","normalized_text":"Northenden"}],"urls":{}},"referenced_tweets":[{"type":"retweeted","id":"1351985810283909121"}],"possibly_sensitive":false,"author_id":"16849521","public_metrics":{"retweet_count":29,"reply_count":0,"like_count":0,"quote_count":0},"id":"1351986670699237380","text":"RT @helenpidd: Severe flood warnings issued for West Didsbury and Northenden meaning the @EnvAgencyNW thinks there’s a danger to life. http…","conversation_id":"1351986670699237380","context_annotations":{},"attachments":{"media_keys":{}}},{"source":"Twitter for iPhone","created_at":"2021-01-20T20:15:05.000Z","lang":"en","entities":{"hashtags":{},"mentions":[{"start":0,"end":10,"username":"TCNAndrew","id":"1340290333"},{"start":11,"end":24,"username":"EnvAgencyYNE","id":"222468030"}],"annotations":{},"urls":{}},"referenced_tweets":[{"type":"replied_to","id":"1351986286379364353"}],"possibly_sensitive":false,"author_id":"27913419","public_metrics":{"retweet_count":0,"reply_count":0,"like_count":1,"quote_count":0},"id":"1351986628483547136","text":"@TCNAndrew @EnvAgencyYNE Ooooh brilliant. Thanks for helping this nosey local 😊","conversation_id":"1351985781842309127","in_reply_to_user_id":"1340290333","context_annotations":{},"attachments":{"media_keys":{}}},{"source":"Twitter for Android","created_at":"2021-01-20T20:15:00.000Z","lang":"en","entities":{"hashtags":{},"mentions":[{"start":3,"end":16,"username":"OfficialWXUK","id":"1215834974919766016"},{"start":68,"end":78,"username":"EnvAgency","id":"47331384"}],"annotations":[{"start":98,"end":110,"probability":0.8692,"type":"Place","normalized_text":"East Didsbury"}],"urls":{}},"referenced_tweets":[{"type":"retweeted","id":"1351985740704579585"}],"possibly_sensitive":false,"author_id":"904235859389624320","public_metrics":{"retweet_count":4,"reply_count":0,"like_count":0,"quote_count":0},"id":"1351986608539643905","text":"RT @OfficialWXUK: Two SEVERE FLOOD WARNINGS have been issued by the @EnvAgency\n\n— River Mersey at East Didsbury\n— River Mersey at West Dids…","conversation_id":"1351986608539643905","context_annotations":{},"attachments":{"media_keys":{}}}]
